[{"n":1,"name":"Athiravile Thirusannidhi","name2":"അതിരാവിലെ തിരുസന്നിധി ","col":"kristheeya-keerthanangal","colName":"Kristheeya Keerthanangal"},{"n":2,"name":"Parane Thirumukha","name2":"പരനെ തിരുമുഖശോഭയിൻ ","col":"kristheeya-keerthanangal","colName":"Kristheeya Keerthanangal"},{"n":3,"name":"Vandhanam Ponnesu Nadha","name2":"വന്ദനം പൊന്നേശുനാഥാ ","col":"kristheeya-keerthanangal","colName":"Kristheeya Keerthanangal"},{"n":4,"name":"Unaruka Nee En","name2":"ഉണരുക നീ എൻ ","col":"kristheeya-keerthanangal","colName":"Kristheeya Keerthanangal"},{"n":5,"name":"Maname pakshiganangal","name2":"മനമെ പക്ഷിഗണങ്ങൾ","col":"kristheeya-keerthanangal","colName":"Kristheeya Keerthanangal"},{"n":6,"name":"Ushakaalam","name2":"ഉഷകാലം","col":"kristheeya-keerthanangal","colName":"Kristheeya Keerthanangal"},{"n":7,"name":"Athmave Unaruka","name2":"","col":"kristheeya-keerthanangal","colName":"Kristheeya Keerthanangal"},{"n":8,"name":"Koode Parka","name2":"","col":"kristheeya-keerthanangal","colName":"Kristheeya Keerthanangal"},{"n":9,"name":"Ennathmavil Athithyane","name2":"","col":"kristheeya-keerthanangal","colName":"Kristheeya Keerthanangal"},{"n":10,"name":"Innu Pakalilenne","name2":"","col":"kristheeya-keerthanangal","colName":"Kristheeya Keerthanangal"},{"n":11,"name":"Karthane","name2":"","col":"kristheeya-keerthanangal","colName":"Kristheeya Keerthanangal"},{"n":12,"name":"Innu Pakalmuzhuvan","name2":"","col":"kristheeya-keerthanangal","colName":"Kristheeya Keerthanangal"},{"n":13,"name":"Sandhe Sooryasthamana","name2":"","col":"kristheeya-keerthanangal","colName":"Kristheeya Keerthanangal"},{"n":14,"name":"Theernnu PakalKaalam","name2":"","col":"kristheeya-keerthanangal","colName":"Kristheeya Keerthanangal"},{"n":15,"name":"Aathiyum Anthavum","name2":"","col":"kristheeya-keerthanangal","colName":"Kristheeya Keerthanangal"},{"n":16,"name":"Shudha Shudha","name2":"","col":"kristheeya-keerthanangal","colName":"Kristheeya Keerthanangal"},{"n":17,"name":"Mannavane Mahonnatha","name2":"","col":"kristheeya-keerthanangal","colName":"Kristheeya Keerthanangal"},{"n":18,"name":"Varika Suradhipa","name2":"","col":"kristheeya-keerthanangal","colName":"Kristheeya Keerthanangal"},{"n":19,"name":"Senayin Yehovaye","name2":"","col":"kristheeya-keerthanangal","colName":"Kristheeya Keerthanangal"},{"n":20,"name":"Paramadhava Nin  Vilasam","name2":"","col":"kristheeya-keerthanangal","colName":"Kristheeya Keerthanangal"},{"n":21,"name":"Bhoovasikal","name2":"","col":"kristheeya-keerthanangal","colName":"Kristheeya Keerthanangal"},{"n":22,"name":"Sarva Manushyare","name2":"","col":"kristheeya-keerthanangal","colName":"Kristheeya Keerthanangal"},{"n":23,"name":"Varuvin Naam Yehovakku","name2":"","col":"kristheeya-keerthanangal","colName":"Kristheeya Keerthanangal"},{"n":24,"name":"Yesuvin Sannidhi Mama","name2":"","col":"kristheeya-keerthanangal","colName":"Kristheeya Keerthanangal"},{"n":25,"name":"Nin Thirumukha Shobha","name2":"","col":"kristheeya-keerthanangal","colName":"Kristheeya Keerthanangal"},{"n":26,"name":"Ashisham Nalkename","name2":"","col":"kristheeya-keerthanangal","colName":"Kristheeya Keerthanangal"},{"n":27,"name":"Anugerha Kadale Ezhunulli","name2":"","col":"kristheeya-keerthanangal","colName":"Kristheeya Keerthanangal"},{"n":28,"name":"Vannidenam Yesu Nadha","name2":"","col":"kristheeya-keerthanangal","colName":"Kristheeya Keerthanangal"},{"n":29,"name":"Varasundhara Varamandala","name2":"","col":"kristheeya-keerthanangal","colName":"Kristheeya Keerthanangal"},{"n":30,"name":"Anpu Thingum","name2":"","col":"kristheeya-keerthanangal","colName":"Kristheeya Keerthanangal"},{"n":31,"name":"Asisamari","name2":"","col":"kristheeya-keerthanangal","colName":"Kristheeya Keerthanangal"},{"n":32,"name":"Yesu Nadha Neethisoorya","name2":"","col":"kristheeya-keerthanangal","colName":"Kristheeya Keerthanangal"},{"n":33,"name":"Sanidhyam","name2":"","col":"kristheeya-keerthanangal","colName":"Kristheeya Keerthanangal"},{"n":34,"name":"Dheva Dheva Thriloka Nadha","name2":"","col":"kristheeya-keerthanangal","colName":"Kristheeya Keerthanangal"},{"n":35,"name":"Yesuve Ee Sabhamel","name2":"","col":"kristheeya-keerthanangal","colName":"Kristheeya Keerthanangal"},{"n":36,"name":"Yesuve Dhyanikkum","name2":"","col":"kristheeya-keerthanangal","colName":"Kristheeya Keerthanangal"},{"n":37,"name":"Yesumaheshane Njan","name2":"","col":"kristheeya-keerthanangal","colName":"Kristheeya Keerthanangal"},{"n":38,"name":"Sreeyesu Namame","name2":"","col":"kristheeya-keerthanangal","colName":"Kristheeya Keerthanangal"},{"n":39,"name":"Yesu Ennulla Naamame","name2":"","col":"kristheeya-keerthanangal","colName":"Kristheeya Keerthanangal"},{"n":40,"name":"Ha Koodi Naam","name2":"","col":"kristheeya-keerthanangal","colName":"Kristheeya Keerthanangal"},{"n":41,"name":"Manasame Sree Yesuve","name2":"","col":"kristheeya-keerthanangal","colName":"Kristheeya Keerthanangal"},{"n":42,"name":"Nadha Choriyaname","name2":"","col":"kristheeya-keerthanangal","colName":"Kristheeya Keerthanangal"},{"n":43,"name":"Sreyesu Naamame","name2":"","col":"kristheeya-keerthanangal","colName":"Kristheeya Keerthanangal"},{"n":44,"name":"Yesuvin Naamam","name2":"","col":"kristheeya-keerthanangal","colName":"Kristheeya Keerthanangal"},{"n":45,"name":"Nadhane En Yesuve","name2":"","col":"kristheeya-keerthanangal","colName":"Kristheeya Keerthanangal"},{"n":46,"name":"Haalelujjha","name2":"","col":"kristheeya-keerthanangal","colName":"Kristheeya Keerthanangal"},{"n":47,"name":"Senakalin","name2":"","col":"kristheeya-keerthanangal","colName":"Kristheeya Keerthanangal"},{"n":48,"name":"Yesudheva Yesunayaka","name2":"","col":"kristheeya-keerthanangal","colName":"Kristheeya Keerthanangal"},{"n":49,"name":"Sthuthippin Sthuthippin","name2":"","col":"kristheeya-keerthanangal","colName":"Kristheeya Keerthanangal"},{"n":50,"name":"Dhevanandhana Vandhanam","name2":"","col":"kristheeya-keerthanangal","colName":"Kristheeya Keerthanangal"},{"n":51,"name":"Yesuvine Sthuthi Nee","name2":"","col":"kristheeya-keerthanangal","colName":"Kristheeya Keerthanangal"},{"n":52,"name":"Sthothramesu Nadhane","name2":"","col":"kristheeya-keerthanangal","colName":"Kristheeya Keerthanangal"},{"n":53,"name":"Sreeyesu Dheva","name2":"","col":"kristheeya-keerthanangal","colName":"Kristheeya Keerthanangal"},{"n":54,"name":"Akhilesha Nandananu","name2":"","col":"kristheeya-keerthanangal","colName":"Kristheeya Keerthanangal"},{"n":55,"name":"Yesumahonnathane","name2":"","col":"kristheeya-keerthanangal","colName":"Kristheeya Keerthanangal"},{"n":56,"name":"Vandhanam Yesupara","name2":"","col":"kristheeya-keerthanangal","colName":"Kristheeya Keerthanangal"},{"n":57,"name":"Karthavine  ","name2":"","col":"kristheeya-keerthanangal","colName":"Kristheeya Keerthanangal"},{"n":58,"name":"Sthothram Sree Manuvelane","name2":"","col":"kristheeya-keerthanangal","colName":"Kristheeya Keerthanangal"},{"n":59,"name":"Sthothram Cheyum","name2":"","col":"kristheeya-keerthanangal","colName":"Kristheeya Keerthanangal"},{"n":60,"name":"Sthothram Ennesupara","name2":"","col":"kristheeya-keerthanangal","colName":"Kristheeya Keerthanangal"},{"n":61,"name":"Sthothram Yesuve","name2":"","col":"kristheeya-keerthanangal","colName":"Kristheeya Keerthanangal"},{"n":62,"name":"Yesunadha Nin Kripakkai","name2":"","col":"kristheeya-keerthanangal","colName":"Kristheeya Keerthanangal"},{"n":63,"name":"Parisudha Parane","name2":"","col":"kristheeya-keerthanangal","colName":"Kristheeya Keerthanangal"},{"n":64,"name":"Aadukalku Vendi","name2":"","col":"kristheeya-keerthanangal","colName":"Kristheeya Keerthanangal"},{"n":65,"name":"Parama Dheyalu","name2":"","col":"kristheeya-keerthanangal","colName":"Kristheeya Keerthanangal"},{"n":66,"name":"Jeevane En Jeevane","name2":"","col":"kristheeya-keerthanangal","colName":"Kristheeya Keerthanangal"},{"n":67,"name":"Ennodulla Nin Sarva","name2":"","col":"kristheeya-keerthanangal","colName":"Kristheeya Keerthanangal"},{"n":68,"name":"Parama Pithavae","name2":"","col":"kristheeya-keerthanangal","colName":"Kristheeya Keerthanangal"},{"n":69,"name":"Vazhthuka Nee Maname","name2":"","col":"kristheeya-keerthanangal","colName":"Kristheeya Keerthanangal"},{"n":70,"name":"Paadi Sthuthi","name2":"","col":"kristheeya-keerthanangal","colName":"Kristheeya Keerthanangal"},{"n":71,"name":"Vandhanam Vandhanam Nadha","name2":"","col":"kristheeya-keerthanangal","colName":"Kristheeya Keerthanangal"},{"n":72,"name":"Manuvela Ninakku Vandhanam","name2":"","col":"kristheeya-keerthanangal","colName":"Kristheeya Keerthanangal"},{"n":73,"name":"Paadum Parama","name2":"","col":"kristheeya-keerthanangal","colName":"Kristheeya Keerthanangal"},{"n":74,"name":"Vaazhthidunnu Vaazhthidunnu","name2":"","col":"kristheeya-keerthanangal","colName":"Kristheeya Keerthanangal"},{"n":75,"name":"Sarvaloka Srishttavakum","name2":"","col":"kristheeya-keerthanangal","colName":"Kristheeya Keerthanangal"},{"n":76,"name":"Pahimaam Jegatheeswara","name2":"","col":"kristheeya-keerthanangal","colName":"Kristheeya Keerthanangal"},{"n":77,"name":"Dhevanu Sadha","name2":"","col":"kristheeya-keerthanangal","colName":"Kristheeya Keerthanangal"},{"n":78,"name":"Enne Veenda  ","name2":"","col":"kristheeya-keerthanangal","colName":"Kristheeya Keerthanangal"},{"n":79,"name":"En atmave vazhthuka ","name2":"","col":"kristheeya-keerthanangal","colName":"Kristheeya Keerthanangal"},{"n":80,"name":"Yesu Nayaka Sreeshanamo","name2":"","col":"kristheeya-keerthanangal","colName":"Kristheeya Keerthanangal"},{"n":81,"name":"Dheivathinu Sthothram","name2":"","col":"kristheeya-keerthanangal","colName":"Kristheeya Keerthanangal"},{"n":82,"name":"Dheva Dhevanu Mangalam","name2":"","col":"kristheeya-keerthanangal","colName":"Kristheeya Keerthanangal"},{"n":83,"name":"Papathin  ","name2":"","col":"kristheeya-keerthanangal","colName":"Kristheeya Keerthanangal"},{"n":84,"name":"Ennalun Sthuthikanam Njan","name2":"","col":"kristheeya-keerthanangal","colName":"Kristheeya Keerthanangal"},{"n":85,"name":"Parisudha Parane","name2":"","col":"kristheeya-keerthanangal","colName":"Kristheeya Keerthanangal"},{"n":86,"name":"Sthuthi sthuthi","name2":"","col":"kristheeya-keerthanangal","colName":"Kristheeya Keerthanangal"},{"n":87,"name":"Rekshakane","name2":"","col":"kristheeya-keerthanangal","colName":"Kristheeya Keerthanangal"},{"n":88,"name":"Paadham Vandhikunne","name2":"","col":"kristheeya-keerthanangal","colName":"Kristheeya Keerthanangal"},{"n":89,"name":"Maanuvelin Sthuthiye","name2":"","col":"kristheeya-keerthanangal","colName":"Kristheeya Keerthanangal"},{"n":90,"name":"Ellarum Yesu Naamathye  ","name2":"","col":"kristheeya-keerthanangal","colName":"Kristheeya Keerthanangal"},{"n":91,"name":"Vazhthin vazhthin ","name2":"","col":"kristheeya-keerthanangal","colName":"Kristheeya Keerthanangal"},{"n":92,"name":"Sthuthichei Maname","name2":"","col":"kristheeya-keerthanangal","colName":"Kristheeya Keerthanangal"},{"n":93,"name":"Maname Pukazhthidu Nee","name2":"","col":"kristheeya-keerthanangal","colName":"Kristheeya Keerthanangal"},{"n":94,"name":"Vandhanam Cheithiduvin","name2":"","col":"kristheeya-keerthanangal","colName":"Kristheeya Keerthanangal"},{"n":95,"name":"Paaduvin ","name2":"","col":"kristheeya-keerthanangal","colName":"Kristheeya Keerthanangal"},{"n":96,"name":"Paadum Njan","name2":"","col":"kristheeya-keerthanangal","colName":"Kristheeya Keerthanangal"},{"n":97,"name":"Paadum Njan Parameshanu","name2":"","col":"kristheeya-keerthanangal","colName":"Kristheeya Keerthanangal"},{"n":98,"name":"Vaazhthidume","name2":"","col":"kristheeya-keerthanangal","colName":"Kristheeya Keerthanangal"},{"n":99,"name":"Pukazhthin","name2":"","col":"kristheeya-keerthanangal","colName":"Kristheeya Keerthanangal"},{"n":100,"name":"Athishaya Kaaruny ","name2":"","col":"kristheeya-keerthanangal","colName":"Kristheeya Keerthanangal"},{"n":101,"name":"Nithyavandanam ","name2":"","col":"kristheeya-keerthanangal","colName":"Kristheeya Keerthanangal"},{"n":102,"name":"Karunakaranam  ","name2":"","col":"kristheeya-keerthanangal","colName":"Kristheeya Keerthanangal"},{"n":103,"name":"Paradheva Sworga ","name2":"","col":"kristheeya-keerthanangal","colName":"Kristheeya Keerthanangal"},{"n":104,"name":"Aadhithya  ","name2":"","col":"kristheeya-keerthanangal","colName":"Kristheeya Keerthanangal"},{"n":105,"name":"Parama Pithaviunu  ","name2":"","col":"kristheeya-keerthanangal","colName":"Kristheeya Keerthanangal"},{"n":106,"name":"Sthuthichiduvin  ","name2":"","col":"kristheeya-keerthanangal","colName":"Kristheeya Keerthanangal"},{"n":107,"name":"Njanennum  ","name2":"","col":"kristheeya-keerthanangal","colName":"Kristheeya Keerthanangal"},{"n":108,"name":"Ennullame  ","name2":"","col":"kristheeya-keerthanangal","colName":"Kristheeya Keerthanangal"},{"n":109,"name":"Sthuthi Geetham  ","name2":"","col":"kristheeya-keerthanangal","colName":"Kristheeya Keerthanangal"},{"n":110,"name":"Onnumillayikayil  ","name2":"","col":"kristheeya-keerthanangal","colName":"Kristheeya Keerthanangal"},{"n":111,"name":"Vaazhthen Dhehi ","name2":"","col":"kristheeya-keerthanangal","colName":"Kristheeya Keerthanangal"},{"n":112,"name":"Yesu naamam ","name2":"","col":"kristheeya-keerthanangal","colName":"Kristheeya Keerthanangal"},{"n":113,"name":"Padin inpageetham ","name2":"","col":"kristheeya-keerthanangal","colName":"Kristheeya Keerthanangal"},{"n":114,"name":"Nararodathy sneham ","name2":"","col":"kristheeya-keerthanangal","colName":"Kristheeya Keerthanangal"},{"n":115,"name":"Kristavare ","name2":"","col":"kristheeya-keerthanangal","colName":"Kristheeya Keerthanangal"},{"n":116,"name":"Aattidayar ","name2":"","col":"kristheeya-keerthanangal","colName":"Kristheeya Keerthanangal"},{"n":117,"name":"Athyalbhuthame ","name2":"","col":"kristheeya-keerthanangal","colName":"Kristheeya Keerthanangal"},{"n":118,"name":"Jathanai  ","name2":"","col":"kristheeya-keerthanangal","colName":"Kristheeya Keerthanangal"},{"n":119,"name":"Paridam mangala ","name2":"","col":"kristheeya-keerthanangal","colName":"Kristheeya Keerthanangal"},{"n":120,"name":"Vagdhatha Sampoorthi ","name2":"","col":"kristheeya-keerthanangal","colName":"Kristheeya Keerthanangal"},{"n":121,"name":"Snehamam Dheva  ","name2":"","col":"kristheeya-keerthanangal","colName":"Kristheeya Keerthanangal"},{"n":122,"name":"Raaja Raaja ","name2":"","col":"kristheeya-keerthanangal","colName":"Kristheeya Keerthanangal"},{"n":123,"name":"Athimangala kaaranane  ","name2":"","col":"kristheeya-keerthanangal","colName":"Kristheeya Keerthanangal"},{"n":124,"name":"Narar Rekshapeduvan  ","name2":"","col":"kristheeya-keerthanangal","colName":"Kristheeya Keerthanangal"},{"n":125,"name":"Albhuthane Yesunadha  ","name2":"","col":"kristheeya-keerthanangal","colName":"Kristheeya Keerthanangal"},{"n":126,"name":"Yesu innu janichu ","name2":"","col":"kristheeya-keerthanangal","colName":"Kristheeya Keerthanangal"},{"n":127,"name":"Bethlehem Nal  ","name2":"","col":"kristheeya-keerthanangal","colName":"Kristheeya Keerthanangal"},{"n":128,"name":"Viswasikale ","name2":"","col":"kristheeya-keerthanangal","colName":"Kristheeya Keerthanangal"},{"n":129,"name":"Kelka dootha ","name2":"","col":"kristheeya-keerthanangal","colName":"Kristheeya Keerthanangal"},{"n":130,"name":"Yesuvin jananathe ","name2":"","col":"kristheeya-keerthanangal","colName":"Kristheeya Keerthanangal"},{"n":131,"name":"Mahiyil Manushavesham ","name2":"","col":"kristheeya-keerthanangal","colName":"Kristheeya Keerthanangal"},{"n":132,"name":"Maru Dhivasam  ","name2":"","col":"kristheeya-keerthanangal","colName":"Kristheeya Keerthanangal"},{"n":133,"name":"Salemin Athipathi ","name2":"","col":"kristheeya-keerthanangal","colName":"Kristheeya Keerthanangal"},{"n":134,"name":"Maanam mahathvam ","name2":"","col":"kristheeya-keerthanangal","colName":"Kristheeya Keerthanangal"},{"n":135,"name":"Hosanna  ","name2":"","col":"kristheeya-keerthanangal","colName":"Kristheeya Keerthanangal"},{"n":136,"name":"Parama Thanayanaakum  ","name2":"","col":"kristheeya-keerthanangal","colName":"Kristheeya Keerthanangal"},{"n":137,"name":"Devesha Yesupara  ","name2":"","col":"kristheeya-keerthanangal","colName":"Kristheeya Keerthanangal"},{"n":138,"name":"Ayyayyo Mahaa ","name2":"","col":"kristheeya-keerthanangal","colName":"Kristheeya Keerthanangal"},{"n":139,"name":"Dheva Dheva Nandhanan ","name2":"","col":"kristheeya-keerthanangal","colName":"Kristheeya Keerthanangal"},{"n":140,"name":"Dhaivame En Dhaivame  ","name2":"","col":"kristheeya-keerthanangal","colName":"Kristheeya Keerthanangal"},{"n":141,"name":"Veenaal  ","name2":"","col":"kristheeya-keerthanangal","colName":"Kristheeya Keerthanangal"},{"n":142,"name":"Vannen Kaalvary ","name2":"","col":"kristheeya-keerthanangal","colName":"Kristheeya Keerthanangal"},{"n":143,"name":"Enthoranpithapane ","name2":"","col":"kristheeya-keerthanangal","colName":"Kristheeya Keerthanangal"},{"n":144,"name":"Deivathinte Eka Puthran  ","name2":"","col":"kristheeya-keerthanangal","colName":"Kristheeya Keerthanangal"},{"n":145,"name":"Ninakkai  ","name2":"","col":"kristheeya-keerthanangal","colName":"Kristheeya Keerthanangal"},{"n":146,"name":"Krusinmel  ","name2":"","col":"kristheeya-keerthanangal","colName":"Kristheeya Keerthanangal"},{"n":147,"name":"Immanuvel  ","name2":"","col":"kristheeya-keerthanangal","colName":"Kristheeya Keerthanangal"},{"n":148,"name":"Sarva Paapa  ","name2":"","col":"kristheeya-keerthanangal","colName":"Kristheeya Keerthanangal"},{"n":149,"name":"Pilarnnoru Paaraye  ","name2":"","col":"kristheeya-keerthanangal","colName":"Kristheeya Keerthanangal"},{"n":150,"name":"Mahathwa prabhu ","name2":"","col":"kristheeya-keerthanangal","colName":"Kristheeya Keerthanangal"},{"n":151,"name":"Sodharare","name2":"","col":"kristheeya-keerthanangal","colName":"Kristheeya Keerthanangal"},{"n":152,"name":"Kalasichu Kadora","name2":"","col":"kristheeya-keerthanangal","colName":"Kristheeya Keerthanangal"},{"n":153,"name":"Jeyam Jeyam ","name2":"","col":"kristheeya-keerthanangal","colName":"Kristheeya Keerthanangal"},{"n":154,"name":"Yesu Kristhu Uyirthu","name2":"","col":"kristheeya-keerthanangal","colName":"Kristheeya Keerthanangal"},{"n":155,"name":"Maranam Jeyicha  ","name2":"","col":"kristheeya-keerthanangal","colName":"Kristheeya Keerthanangal"},{"n":156,"name":"Innesurajan","name2":"","col":"kristheeya-keerthanangal","colName":"Kristheeya Keerthanangal"},{"n":157,"name":"Jeevanayakane","name2":"","col":"kristheeya-keerthanangal","colName":"Kristheeya Keerthanangal"},{"n":158,"name":"Kristhu veendum ","name2":"","col":"kristheeya-keerthanangal","colName":"Kristheeya Keerthanangal"},{"n":159,"name":"Mahimapathi","name2":"","col":"kristheeya-keerthanangal","colName":"Kristheeya Keerthanangal"},{"n":160,"name":"Vaanalokathezhunnulli","name2":"","col":"kristheeya-keerthanangal","colName":"Kristheeya Keerthanangal"},{"n":161,"name":"Mulkireedathal","name2":"","col":"kristheeya-keerthanangal","colName":"Kristheeya Keerthanangal"},{"n":162,"name":"Dheham Mannakumunpe","name2":"","col":"kristheeya-keerthanangal","colName":"Kristheeya Keerthanangal"},{"n":163,"name":"Paapikalin Rekshakan","name2":"","col":"kristheeya-keerthanangal","colName":"Kristheeya Keerthanangal"},{"n":164,"name":"Rakshithavine ","name2":"","col":"kristheeya-keerthanangal","colName":"Kristheeya Keerthanangal"},{"n":165,"name":"Manamayamaam","name2":"","col":"kristheeya-keerthanangal","colName":"Kristheeya Keerthanangal"},{"n":166,"name":"Yesuvinnarukil Vaa Paapi","name2":"","col":"kristheeya-keerthanangal","colName":"Kristheeya Keerthanangal"},{"n":167,"name":"Paramanandham","name2":"","col":"kristheeya-keerthanangal","colName":"Kristheeya Keerthanangal"},{"n":168,"name":"Nasaryanaakum","name2":"","col":"kristheeya-keerthanangal","colName":"Kristheeya Keerthanangal"},{"n":169,"name":"Paapi Paranarikil","name2":"","col":"kristheeya-keerthanangal","colName":"Kristheeya Keerthanangal"},{"n":170,"name":"Njan Chaitha Paathakam","name2":"","col":"kristheeya-keerthanangal","colName":"Kristheeya Keerthanangal"},{"n":171,"name":"Melveettil ","name2":"","col":"kristheeya-keerthanangal","colName":"Kristheeya Keerthanangal"},{"n":172,"name":"Nee ksheenicho","name2":"","col":"kristheeya-keerthanangal","colName":"Kristheeya Keerthanangal"},{"n":173,"name":"Enthu Nallor","name2":"","col":"kristheeya-keerthanangal","colName":"Kristheeya Keerthanangal"},{"n":174,"name":"Maruthalikkum","name2":"","col":"kristheeya-keerthanangal","colName":"Kristheeya Keerthanangal"},{"n":175,"name":"Odiva Kripayam","name2":"","col":"kristheeya-keerthanangal","colName":"Kristheeya Keerthanangal"},{"n":176,"name":"Sudhikai","name2":"","col":"kristheeya-keerthanangal","colName":"Kristheeya Keerthanangal"},{"n":177,"name":"Pinnale Varika","name2":"","col":"kristheeya-keerthanangal","colName":"Kristheeya Keerthanangal"},{"n":178,"name":"Vilayeriya Kaalam ","name2":"","col":"kristheeya-keerthanangal","colName":"Kristheeya Keerthanangal"},{"n":179,"name":"Loka shoka Sagare","name2":"","col":"kristheeya-keerthanangal","colName":"Kristheeya Keerthanangal"},{"n":180,"name":"Jeevanundaam eka","name2":"","col":"kristheeya-keerthanangal","colName":"Kristheeya Keerthanangal"},{"n":181,"name":"Vaneeduvin","name2":"","col":"kristheeya-keerthanangal","colName":"Kristheeya Keerthanangal"},{"n":182,"name":"Jeevitha Yathrakara","name2":"","col":"kristheeya-keerthanangal","colName":"Kristheeya Keerthanangal"},{"n":183,"name":"Jeevitha Paatha","name2":"","col":"kristheeya-keerthanangal","colName":"Kristheeya Keerthanangal"},{"n":184,"name":"Thanaya ninnudae","name2":"","col":"kristheeya-keerthanangal","colName":"Kristheeya Keerthanangal"},{"n":185,"name":"Ayo Paapi","name2":"","col":"kristheeya-keerthanangal","colName":"Kristheeya Keerthanangal"},{"n":186,"name":"En jeevan ","name2":"","col":"kristheeya-keerthanangal","colName":"Kristheeya Keerthanangal"},{"n":187,"name":"Varika Nalvarangale","name2":"","col":"kristheeya-keerthanangal","colName":"Kristheeya Keerthanangal"},{"n":188,"name":"Vannavasika","name2":"","col":"kristheeya-keerthanangal","colName":"Kristheeya Keerthanangal"},{"n":189,"name":"Athmave Vaniduka","name2":"","col":"kristheeya-keerthanangal","colName":"Kristheeya Keerthanangal"},{"n":190,"name":"Visudhathmave ","name2":"","col":"kristheeya-keerthanangal","colName":"Kristheeya Keerthanangal"},{"n":191,"name":"Maa Parisudhathmane","name2":"","col":"kristheeya-keerthanangal","colName":"Kristheeya Keerthanangal"},{"n":192,"name":"Penthicosthin Vallabhane","name2":"","col":"kristheeya-keerthanangal","colName":"Kristheeya Keerthanangal"},{"n":193,"name":"Sudha sudha Karhadheva ","name2":"","col":"kristheeya-keerthanangal","colName":"Kristheeya Keerthanangal"},{"n":194,"name":"Ennullilennum","name2":"","col":"kristheeya-keerthanangal","colName":"Kristheeya Keerthanangal"},{"n":195,"name":"Paavanathmadhanam","name2":"","col":"kristheeya-keerthanangal","colName":"Kristheeya Keerthanangal"},{"n":196,"name":"Penthicosthin Shakthiye","name2":"","col":"kristheeya-keerthanangal","colName":"Kristheeya Keerthanangal"},{"n":197,"name":"Parisudhathmave","name2":"","col":"kristheeya-keerthanangal","colName":"Kristheeya Keerthanangal"},{"n":198,"name":"Nin Thiru Vachanathil  ","name2":"","col":"kristheeya-keerthanangal","colName":"Kristheeya Keerthanangal"},{"n":199,"name":"Nalla Dhevane","name2":"","col":"kristheeya-keerthanangal","colName":"Kristheeya Keerthanangal"},{"n":200,"name":"Dhaiva Vachaname","name2":"","col":"kristheeya-keerthanangal","colName":"Kristheeya Keerthanangal"},{"n":201,"name":"Yesuvin Thiru ","name2":"","col":"kristheeya-keerthanangal","colName":"Kristheeya Keerthanangal"},{"n":202,"name":"Madhuram New ","name2":"","col":"kristheeya-keerthanangal","colName":"Kristheeya Keerthanangal"},{"n":203,"name":"Daivame nin ","name2":"","col":"kristheeya-keerthanangal","colName":"Kristheeya Keerthanangal"},{"n":204,"name":"Paapi ","name2":"","col":"kristheeya-keerthanangal","colName":"Kristheeya Keerthanangal"},{"n":205,"name":"Parane  ","name2":"","col":"kristheeya-keerthanangal","colName":"Kristheeya Keerthanangal"},{"n":206,"name":"Sree Devaattin Kutty","name2":"","col":"kristheeya-keerthanangal","colName":"Kristheeya Keerthanangal"},{"n":207,"name":"Enthu Cheyyendu ","name2":"","col":"kristheeya-keerthanangal","colName":"Kristheeya Keerthanangal"},{"n":208,"name":"Kumbidunne  ","name2":"","col":"kristheeya-keerthanangal","colName":"Kristheeya Keerthanangal"},{"n":209,"name":"Jeeva Naayakanam Yesuve","name2":"","col":"kristheeya-keerthanangal","colName":"Kristheeya Keerthanangal"},{"n":210,"name":"Yesuve karunasana","name2":"","col":"kristheeya-keerthanangal","colName":"Kristheeya Keerthanangal"},{"n":211,"name":"Daivame Sneha Roopane","name2":"","col":"kristheeya-keerthanangal","colName":"Kristheeya Keerthanangal"},{"n":212,"name":"Yesuve  ","name2":"","col":"kristheeya-keerthanangal","colName":"Kristheeya Keerthanangal"},{"n":213,"name":"Anpin Roopi","name2":"","col":"kristheeya-keerthanangal","colName":"Kristheeya Keerthanangal"},{"n":214,"name":"Yesuvepole","name2":"","col":"kristheeya-keerthanangal","colName":"Kristheeya Keerthanangal"},{"n":215,"name":"Neeyozhike ","name2":"","col":"kristheeya-keerthanangal","colName":"Kristheeya Keerthanangal"},{"n":216,"name":"Snehamam Yesuve  ","name2":"","col":"kristheeya-keerthanangal","colName":"Kristheeya Keerthanangal"},{"n":217,"name":"Mahathwa Prabhu Maricha Van","name2":"","col":"kristheeya-keerthanangal","colName":"Kristheeya Keerthanangal"},{"n":218,"name":"Swantham","name2":"","col":"kristheeya-keerthanangal","colName":"Kristheeya Keerthanangal"},{"n":219,"name":"Yesuvin Swontham  ","name2":"","col":"kristheeya-keerthanangal","colName":"Kristheeya Keerthanangal"},{"n":220,"name":"Njan varunnu ","name2":"","col":"kristheeya-keerthanangal","colName":"Kristheeya Keerthanangal"},{"n":221,"name":"Murivetta ","name2":"","col":"kristheeya-keerthanangal","colName":"Kristheeya Keerthanangal"},{"n":222,"name":"Thetty njan ","name2":"","col":"kristheeya-keerthanangal","colName":"Kristheeya Keerthanangal"},{"n":223,"name":"En Daivame","name2":"","col":"kristheeya-keerthanangal","colName":"Kristheeya Keerthanangal"},{"n":224,"name":"Sevichidum","name2":"","col":"kristheeya-keerthanangal","colName":"Kristheeya Keerthanangal"},{"n":225,"name":"Ninte Hitham","name2":"","col":"kristheeya-keerthanangal","colName":"Kristheeya Keerthanangal"},{"n":226,"name":"Daivahitham ","name2":"","col":"kristheeya-keerthanangal","colName":"Kristheeya Keerthanangal"},{"n":227,"name":"Ninnishtam deva ","name2":"","col":"kristheeya-keerthanangal","colName":"Kristheeya Keerthanangal"},{"n":228,"name":"Atmadehi Dhehathe","name2":"","col":"kristheeya-keerthanangal","colName":"Kristheeya Keerthanangal"},{"n":229,"name":"Sworgeeya Pithave  ","name2":"","col":"kristheeya-keerthanangal","colName":"Kristheeya Keerthanangal"},{"n":230,"name":"Kurisheduthen","name2":"","col":"kristheeya-keerthanangal","colName":"Kristheeya Keerthanangal"},{"n":231,"name":"Ellam Ange Mahathuathinai","name2":"","col":"kristheeya-keerthanangal","colName":"Kristheeya Keerthanangal"},{"n":232,"name":"En Dheepame","name2":"","col":"kristheeya-keerthanangal","colName":"Kristheeya Keerthanangal"},{"n":233,"name":"En Yesu En Priyan ","name2":"","col":"kristheeya-keerthanangal","colName":"Kristheeya Keerthanangal"},{"n":234,"name":"Sweekarikken ","name2":"","col":"kristheeya-keerthanangal","colName":"Kristheeya Keerthanangal"},{"n":235,"name":"Lokamam  ","name2":"","col":"kristheeya-keerthanangal","colName":"Kristheeya Keerthanangal"},{"n":236,"name":"Enikkay Chinthi  ","name2":"","col":"kristheeya-keerthanangal","colName":"Kristheeya Keerthanangal"},{"n":237,"name":"Yesu En Adisthana  ","name2":"","col":"kristheeya-keerthanangal","colName":"Kristheeya Keerthanangal"},{"n":238,"name":"En yesu En Sangeetham ","name2":"","col":"kristheeya-keerthanangal","colName":"Kristheeya Keerthanangal"},{"n":239,"name":" Kristhuvinte Dhaman","name2":"","col":"kristheeya-keerthanangal","colName":"Kristheeya Keerthanangal"},{"n":240,"name":"Onnum Bhayapedenda ","name2":"","col":"kristheeya-keerthanangal","colName":"Kristheeya Keerthanangal"},{"n":241,"name":"Ninnoden Daivame ","name2":"","col":"kristheeya-keerthanangal","colName":"Kristheeya Keerthanangal"},{"n":242,"name":"Snehathin Idayanam","name2":"","col":"kristheeya-keerthanangal","colName":"Kristheeya Keerthanangal"},{"n":243,"name":"Yesu Mathieniku","name2":"","col":"kristheeya-keerthanangal","colName":"Kristheeya Keerthanangal"},{"n":244,"name":"Paapa Kadam Theerkuvan","name2":"","col":"kristheeya-keerthanangal","colName":"Kristheeya Keerthanangal"},{"n":245,"name":"Ente Sampathennu ","name2":"","col":"kristheeya-keerthanangal","colName":"Kristheeya Keerthanangal"},{"n":246,"name":"En rakshakanam yesu ","name2":"","col":"kristheeya-keerthanangal","colName":"Kristheeya Keerthanangal"},{"n":247,"name":"Neeyallo ","name2":"","col":"kristheeya-keerthanangal","colName":"Kristheeya Keerthanangal"},{"n":248,"name":"Ente Daivam Mahathua ","name2":"","col":"kristheeya-keerthanangal","colName":"Kristheeya Keerthanangal"},{"n":249,"name":"Ente Dayvam Swarga ","name2":"","col":"kristheeya-keerthanangal","colName":"Kristheeya Keerthanangal"},{"n":250,"name":"En Rakshaka ","name2":"","col":"kristheeya-keerthanangal","colName":"Kristheeya Keerthanangal"},{"n":251,"name":"Yesu En Swontham","name2":"","col":"kristheeya-keerthanangal","colName":"Kristheeya Keerthanangal"},{"n":252,"name":"Sree Yesu Nayaka ","name2":"","col":"kristheeya-keerthanangal","colName":"Kristheeya Keerthanangal"},{"n":253,"name":"Yesu en ","name2":"","col":"kristheeya-keerthanangal","colName":"Kristheeya Keerthanangal"},{"n":254,"name":"Kunjattin","name2":"","col":"kristheeya-keerthanangal","colName":"Kristheeya Keerthanangal"},{"n":255,"name":"Dhivathin Rajyam","name2":"","col":"kristheeya-keerthanangal","colName":"Kristheeya Keerthanangal"},{"n":256,"name":"Yesu Aarilum","name2":"","col":"kristheeya-keerthanangal","colName":"Kristheeya Keerthanangal"},{"n":257,"name":"Yesu Dheva ","name2":"","col":"kristheeya-keerthanangal","colName":"Kristheeya Keerthanangal"},{"n":258,"name":"Dayvame Ethra ","name2":"","col":"kristheeya-keerthanangal","colName":"Kristheeya Keerthanangal"},{"n":259,"name":"Paadi Pukazhthidam","name2":"","col":"kristheeya-keerthanangal","colName":"Kristheeya Keerthanangal"},{"n":260,"name":"Sukha Kaalathilum","name2":"","col":"kristheeya-keerthanangal","colName":"Kristheeya Keerthanangal"},{"n":261,"name":"Ennum Nallavan ","name2":"","col":"kristheeya-keerthanangal","colName":"Kristheeya Keerthanangal"},{"n":262,"name":"Thuna Enikkesuvam ","name2":"","col":"kristheeya-keerthanangal","colName":"Kristheeya Keerthanangal"},{"n":263,"name":"Kripayerum","name2":"","col":"kristheeya-keerthanangal","colName":"Kristheeya Keerthanangal"},{"n":264,"name":"Yesuve En Prananayaka","name2":"","col":"kristheeya-keerthanangal","colName":"Kristheeya Keerthanangal"},{"n":265,"name":"Jeevante ","name2":"","col":"kristheeya-keerthanangal","colName":"Kristheeya Keerthanangal"},{"n":266,"name":"En atmave  ","name2":"","col":"kristheeya-keerthanangal","colName":"Kristheeya Keerthanangal"},{"n":267,"name":"En nadhane","name2":"","col":"kristheeya-keerthanangal","colName":"Kristheeya Keerthanangal"},{"n":268,"name":"Njanente Kannukal","name2":"","col":"kristheeya-keerthanangal","colName":"Kristheeya Keerthanangal"},{"n":269,"name":"Yesu En Abhaya Kendhram","name2":"","col":"kristheeya-keerthanangal","colName":"Kristheeya Keerthanangal"},{"n":270,"name":"Enikethu Nerathilum","name2":"","col":"kristheeya-keerthanangal","colName":"Kristheeya Keerthanangal"},{"n":271,"name":"Mahimaezhum","name2":"","col":"kristheeya-keerthanangal","colName":"Kristheeya Keerthanangal"},{"n":272,"name":"Asruthavalsalane","name2":"","col":"kristheeya-keerthanangal","colName":"Kristheeya Keerthanangal"},{"n":273,"name":"Ellam Yesume ","name2":"","col":"kristheeya-keerthanangal","colName":"Kristheeya Keerthanangal"},{"n":274,"name":"Atmavam  ","name2":"","col":"kristheeya-keerthanangal","colName":"Kristheeya Keerthanangal"},{"n":275,"name":"Anugrahathin Adhipathi","name2":"","col":"kristheeya-keerthanangal","colName":"Kristheeya Keerthanangal"},{"n":276,"name":"Kanunnu Njaan ","name2":"","col":"kristheeya-keerthanangal","colName":"Kristheeya Keerthanangal"},{"n":277,"name":"Onne Ullenikanandham","name2":"","col":"kristheeya-keerthanangal","colName":"Kristheeya Keerthanangal"},{"n":278,"name":"Kurishin Nizhalin ","name2":"","col":"kristheeya-keerthanangal","colName":"Kristheeya Keerthanangal"},{"n":279,"name":"Enikai Oruthama Sambath","name2":"","col":"kristheeya-keerthanangal","colName":"Kristheeya Keerthanangal"},{"n":280,"name":"Yahova daivamam","name2":"","col":"kristheeya-keerthanangal","colName":"Kristheeya Keerthanangal"},{"n":281,"name":"Karthan enne  ","name2":"","col":"kristheeya-keerthanangal","colName":"Kristheeya Keerthanangal"},{"n":282,"name":"Yesu kayyil ","name2":"","col":"kristheeya-keerthanangal","colName":"Kristheeya Keerthanangal"},{"n":283,"name":"Ariyatha ","name2":"","col":"kristheeya-keerthanangal","colName":"Kristheeya Keerthanangal"},{"n":284,"name":"Dhukathinte Paana Paathram","name2":"","col":"kristheeya-keerthanangal","colName":"Kristheeya Keerthanangal"},{"n":285,"name":"Visudhar koottam ","name2":"","col":"kristheeya-keerthanangal","colName":"Kristheeya Keerthanangal"},{"n":286,"name":"Ha Etra Bhagyam  ","name2":"","col":"kristheeya-keerthanangal","colName":"Kristheeya Keerthanangal"},{"n":287,"name":"Eppozhum ","name2":"","col":"kristheeya-keerthanangal","colName":"Kristheeya Keerthanangal"},{"n":288,"name":"Aanandhamundeniku","name2":"","col":"kristheeya-keerthanangal","colName":"Kristheeya Keerthanangal"},{"n":289,"name":"Shobhitha Pattanam  ","name2":"","col":"kristheeya-keerthanangal","colName":"Kristheeya Keerthanangal"},{"n":290,"name":"Karthrukahalam  ","name2":"","col":"kristheeya-keerthanangal","colName":"Kristheeya Keerthanangal"},{"n":291,"name":"Bhagyrajyam ","name2":"","col":"kristheeya-keerthanangal","colName":"Kristheeya Keerthanangal"},{"n":292,"name":"Nithya veed ","name2":"","col":"kristheeya-keerthanangal","colName":"Kristheeya Keerthanangal"},{"n":293,"name":"Yerushalemin Imbha Veede ","name2":"","col":"kristheeya-keerthanangal","colName":"Kristheeya Keerthanangal"},{"n":294,"name":"Rajan mumpil  ","name2":"","col":"kristheeya-keerthanangal","colName":"Kristheeya Keerthanangal"},{"n":295,"name":"Ethra Ethra Sreshttam","name2":"","col":"kristheeya-keerthanangal","colName":"Kristheeya Keerthanangal"},{"n":296,"name":"Shobhayerum  ","name2":"","col":"kristheeya-keerthanangal","colName":"Kristheeya Keerthanangal"},{"n":297,"name":"Aarivar ","name2":"","col":"kristheeya-keerthanangal","colName":"Kristheeya Keerthanangal"},{"n":298,"name":"Sworga Bhagyam ","name2":"","col":"kristheeya-keerthanangal","colName":"Kristheeya Keerthanangal"},{"n":299,"name":"Modham Athi Modham","name2":"","col":"kristheeya-keerthanangal","colName":"Kristheeya Keerthanangal"},{"n":300,"name":"Viyhacheeduka ","name2":"","col":"kristheeya-keerthanangal","colName":"Kristheeya Keerthanangal"},{"n":301,"name":"Velackku velackku ","name2":"","col":"kristheeya-keerthanangal","colName":"Kristheeya Keerthanangal"},{"n":302,"name":"Verum kaiyay","name2":"","col":"kristheeya-keerthanangal","colName":"Kristheeya Keerthanangal"},{"n":303,"name":"Suvishesham ","name2":"","col":"kristheeya-keerthanangal","colName":"Kristheeya Keerthanangal"},{"n":304,"name":"Engum Pukazhthin ","name2":"","col":"kristheeya-keerthanangal","colName":"Kristheeya Keerthanangal"},{"n":305,"name":"Suvishesha Koshanamae","name2":"","col":"kristheeya-keerthanangal","colName":"Kristheeya Keerthanangal"},{"n":306,"name":"Padham Padham ","name2":"","col":"kristheeya-keerthanangal","colName":"Kristheeya Keerthanangal"},{"n":307,"name":"Koyithundu Adhikam","name2":"","col":"kristheeya-keerthanangal","colName":"Kristheeya Keerthanangal"},{"n":308,"name":"Yesu Paran ","name2":"","col":"kristheeya-keerthanangal","colName":"Kristheeya Keerthanangal"},{"n":309,"name":"Yesu Nadhan ","name2":"","col":"kristheeya-keerthanangal","colName":"Kristheeya Keerthanangal"},{"n":310,"name":"Jeyikume ","name2":"","col":"kristheeya-keerthanangal","colName":"Kristheeya Keerthanangal"},{"n":311,"name":"Aadithyan ","name2":"","col":"kristheeya-keerthanangal","colName":"Kristheeya Keerthanangal"},{"n":312,"name":"Sathyathinte ","name2":"","col":"kristheeya-keerthanangal","colName":"Kristheeya Keerthanangal"},{"n":313,"name":"Manassode  ","name2":"","col":"kristheeya-keerthanangal","colName":"Kristheeya Keerthanangal"},{"n":314,"name":"Ponnesu ","name2":"","col":"kristheeya-keerthanangal","colName":"Kristheeya Keerthanangal"},{"n":315,"name":"Sneha Virunnu ","name2":"","col":"kristheeya-keerthanangal","colName":"Kristheeya Keerthanangal"},{"n":316,"name":"Mannaye Bhuoojika","name2":"","col":"kristheeya-keerthanangal","colName":"Kristheeya Keerthanangal"},{"n":317,"name":"Paraneshuvae Karunidae","name2":"","col":"kristheeya-keerthanangal","colName":"Kristheeya Keerthanangal"},{"n":318,"name":"Krupayulla ","name2":"","col":"kristheeya-keerthanangal","colName":"Kristheeya Keerthanangal"},{"n":319,"name":"Aadya vivaha  ","name2":"","col":"kristheeya-keerthanangal","colName":"Kristheeya Keerthanangal"},{"n":320,"name":"Yesu Nayaka Vannalum NEW","name2":"","col":"kristheeya-keerthanangal","colName":"Kristheeya Keerthanangal"},{"n":321,"name":"Yehovaye Bhayapettu","name2":"","col":"kristheeya-keerthanangal","colName":"Kristheeya Keerthanangal"},{"n":322,"name":"Manuel mannavane","name2":"","col":"kristheeya-keerthanangal","colName":"Kristheeya Keerthanangal"},{"n":323,"name":"Aaru Sahayikkum ","name2":"","col":"kristheeya-keerthanangal","colName":"Kristheeya Keerthanangal"},{"n":324,"name":"Kristhanmel ","name2":"","col":"kristheeya-keerthanangal","colName":"Kristheeya Keerthanangal"},{"n":325,"name":"Samayamaam ","name2":"","col":"kristheeya-keerthanangal","colName":"Kristheeya Keerthanangal"},{"n":326,"name":"Paralokadhipane","name2":"","col":"kristheeya-keerthanangal","colName":"Kristheeya Keerthanangal"},{"n":327,"name":"Karthave Varenme  ","name2":"","col":"kristheeya-keerthanangal","colName":"Kristheeya Keerthanangal"},{"n":328,"name":"Kaanum vare  ","name2":"","col":"kristheeya-keerthanangal","colName":"Kristheeya Keerthanangal"},{"n":329,"name":"Anugrahathode ","name2":"","col":"kristheeya-keerthanangal","colName":"Kristheeya Keerthanangal"},{"n":330,"name":"Yahova ninte ","name2":"","col":"kristheeya-keerthanangal","colName":"Kristheeya Keerthanangal"},{"n":331,"name":"Swarga rajya","name2":"","col":"kristheeya-keerthanangal","colName":"Kristheeya Keerthanangal"},{"n":332,"name":"Kristhuvin snehathil ","name2":"","col":"kristheeya-keerthanangal","colName":"Kristheeya Keerthanangal"},{"n":333,"name":"Varuvin Cheru Paithangal ","name2":"","col":"kristheeya-keerthanangal","colName":"Kristheeya Keerthanangal"},{"n":334,"name":"Yesuve Pol Avaneniku ","name2":"","col":"kristheeya-keerthanangal","colName":"Kristheeya Keerthanangal"},{"n":335,"name":"Kristu mumbil","name2":"","col":"kristheeya-keerthanangal","colName":"Kristheeya Keerthanangal"},{"n":336,"name":"Baalarakunna ","name2":"","col":"kristheeya-keerthanangal","colName":"Kristheeya Keerthanangal"},{"n":337,"name":"Saanthanakum ","name2":"","col":"kristheeya-keerthanangal","colName":"Kristheeya Keerthanangal"},{"n":338,"name":"Srastavine","name2":"","col":"kristheeya-keerthanangal","colName":"Kristheeya Keerthanangal"},{"n":339,"name":"Thiu Chevi ","name2":"","col":"kristheeya-keerthanangal","colName":"Kristheeya Keerthanangal"},{"n":340,"name":"Paaduvin Sakala Bhoomiye","name2":"","col":"kristheeya-keerthanangal","colName":"Kristheeya Keerthanangal"},{"n":341,"name":"Manujan Ivan Bhagya","name2":"","col":"kristheeya-keerthanangal","colName":"Kristheeya Keerthanangal"},{"n":342,"name":"Ee Para Devanaho","name2":"","col":"kristheeya-keerthanangal","colName":"Kristheeya Keerthanangal"},{"n":343,"name":"Yahenna Dhaivam","name2":"","col":"kristheeya-keerthanangal","colName":"Kristheeya Keerthanangal"},{"n":344,"name":"Jeevanayaka ","name2":"","col":"kristheeya-keerthanangal","colName":"Kristheeya Keerthanangal"},{"n":345,"name":"Parama Thathante","name2":"","col":"kristheeya-keerthanangal","colName":"Kristheeya Keerthanangal"},{"n":346,"name":"Unarnnezhunelka ","name2":"","col":"kristheeya-keerthanangal","colName":"Kristheeya Keerthanangal"},{"n":347,"name":"Zeeone Nee ","name2":"","col":"kristheeya-keerthanangal","colName":"Kristheeya Keerthanangal"},{"n":348,"name":"Yesu Mahesha ","name2":"","col":"kristheeya-keerthanangal","colName":"Kristheeya Keerthanangal"},{"n":349,"name":"Kelka Ente ","name2":"","col":"kristheeya-keerthanangal","colName":"Kristheeya Keerthanangal"},{"n":350,"name":"Pokalle  ","name2":"","col":"kristheeya-keerthanangal","colName":"Kristheeya Keerthanangal"},{"n":351,"name":"Dhaiva Kripa Manoharame ","name2":"","col":"kristheeya-keerthanangal","colName":"Kristheeya Keerthanangal"},{"n":352,"name":"Krupa Krupa  ","name2":"","col":"kristheeya-keerthanangal","colName":"Kristheeya Keerthanangal"},{"n":353,"name":"Dhaiva Krupayil","name2":"","col":"kristheeya-keerthanangal","colName":"Kristheeya Keerthanangal"},{"n":354,"name":"Ponnesu Thampuraan New ","name2":"","col":"kristheeya-keerthanangal","colName":"Kristheeya Keerthanangal"},{"n":355,"name":"Mahalbudhame ","name2":"","col":"kristheeya-keerthanangal","colName":"Kristheeya Keerthanangal"},{"n":356,"name":"Snehamam Thatha ","name2":"","col":"kristheeya-keerthanangal","colName":"Kristheeya Keerthanangal"},{"n":357,"name":"Ma Paapi ","name2":"","col":"kristheeya-keerthanangal","colName":"Kristheeya Keerthanangal"},{"n":358,"name":"Thedi Vannu","name2":"","col":"kristheeya-keerthanangal","colName":"Kristheeya Keerthanangal"},{"n":359,"name":"Mahal Sneham ","name2":"","col":"kristheeya-keerthanangal","colName":"Kristheeya Keerthanangal"},{"n":360,"name":"Yesuvin Snehamo","name2":"","col":"kristheeya-keerthanangal","colName":"Kristheeya Keerthanangal"},{"n":361,"name":"Njan Paapiyairunnunesu","name2":"","col":"kristheeya-keerthanangal","colName":"Kristheeya Keerthanangal"},{"n":362,"name":"Kaanuka Nee Ee","name2":"","col":"kristheeya-keerthanangal","colName":"Kristheeya Keerthanangal"},{"n":363,"name":"SthothrangalPaadi","name2":"","col":"kristheeya-keerthanangal","colName":"Kristheeya Keerthanangal"},{"n":364,"name":"Athisayame","name2":"","col":"kristheeya-keerthanangal","colName":"Kristheeya Keerthanangal"},{"n":365,"name":"Daivasnaham ","name2":"","col":"kristheeya-keerthanangal","colName":"Kristheeya Keerthanangal"},{"n":366,"name":"Enthathishayame","name2":"","col":"kristheeya-keerthanangal","colName":"Kristheeya Keerthanangal"},{"n":367,"name":"Yesuvin Divya  ","name2":"","col":"kristheeya-keerthanangal","colName":"Kristheeya Keerthanangal"},{"n":368,"name":"Inneram ","name2":"","col":"kristheeya-keerthanangal","colName":"Kristheeya Keerthanangal"},{"n":369,"name":"Prarthana Kelkaname ","name2":"","col":"kristheeya-keerthanangal","colName":"Kristheeya Keerthanangal"},{"n":370,"name":"Ente Pranasakhi","name2":"","col":"kristheeya-keerthanangal","colName":"Kristheeya Keerthanangal"},{"n":371,"name":"Uyirthidu Njan","name2":"","col":"kristheeya-keerthanangal","colName":"Kristheeya Keerthanangal"},{"n":372,"name":"Sarva Shakthan ","name2":"","col":"kristheeya-keerthanangal","colName":"Kristheeya Keerthanangal"},{"n":373,"name":"Parane ","name2":"","col":"kristheeya-keerthanangal","colName":"Kristheeya Keerthanangal"},{"n":374,"name":"Ninnodu","name2":"","col":"kristheeya-keerthanangal","colName":"Kristheeya Keerthanangal"},{"n":375,"name":"Prardhanakutharam","name2":"","col":"kristheeya-keerthanangal","colName":"Kristheeya Keerthanangal"},{"n":376,"name":"Dhaivame Threeyekane","name2":"","col":"kristheeya-keerthanangal","colName":"Kristheeya Keerthanangal"},{"n":377,"name":"Parama ","name2":"","col":"kristheeya-keerthanangal","colName":"Kristheeya Keerthanangal"},{"n":378,"name":"Prarthanayin  ","name2":"","col":"kristheeya-keerthanangal","colName":"Kristheeya Keerthanangal"},{"n":379,"name":"Jayam Jayam kollum ","name2":"","col":"kristheeya-keerthanangal","colName":"Kristheeya Keerthanangal"},{"n":380,"name":"Enkristhan Yodhavakuvan","name2":"","col":"kristheeya-keerthanangal","colName":"Kristheeya Keerthanangal"},{"n":381,"name":"Yudhathinu  ","name2":"","col":"kristheeya-keerthanangal","colName":"Kristheeya Keerthanangal"},{"n":382,"name":"Ente Thozharare  ","name2":"","col":"kristheeya-keerthanangal","colName":"Kristheeya Keerthanangal"},{"n":383,"name":"Ninneedin Yesu  ","name2":"","col":"kristheeya-keerthanangal","colName":"Kristheeya Keerthanangal"},{"n":384,"name":"Christya Synyame  ","name2":"","col":"kristheeya-keerthanangal","colName":"Kristheeya Keerthanangal"},{"n":385,"name":"Viswasikale  ","name2":"","col":"kristheeya-keerthanangal","colName":"Kristheeya Keerthanangal"},{"n":386,"name":"Raathriyitha ","name2":"","col":"kristheeya-keerthanangal","colName":"Kristheeya Keerthanangal"},{"n":387,"name":"Njanum Ente Bhavanavum ","name2":"","col":"kristheeya-keerthanangal","colName":"Kristheeya Keerthanangal"},{"n":388,"name":"Kantha Thamasam Enthaho","name2":"","col":"kristheeya-keerthanangal","colName":"Kristheeya Keerthanangal"},{"n":389,"name":"Ennu Nee Vanneedum","name2":"","col":"kristheeya-keerthanangal","colName":"Kristheeya Keerthanangal"},{"n":390,"name":"Yesuvarum Vegathil ","name2":"","col":"kristheeya-keerthanangal","colName":"Kristheeya Keerthanangal"},{"n":391,"name":"Yesurajan ","name2":"","col":"kristheeya-keerthanangal","colName":"Kristheeya Keerthanangal"},{"n":392,"name":"Yesuvodu Chernirippathu","name2":"","col":"kristheeya-keerthanangal","colName":"Kristheeya Keerthanangal"},{"n":393,"name":"Kalvariyil ","name2":"","col":"kristheeya-keerthanangal","colName":"Kristheeya Keerthanangal"},{"n":394,"name":"Manavare  ","name2":"","col":"kristheeya-keerthanangal","colName":"Kristheeya Keerthanangal"},{"n":395,"name":"Anandha ","name2":"","col":"kristheeya-keerthanangal","colName":"Kristheeya Keerthanangal"},{"n":396,"name":"Sudher Stuthikum ","name2":"","col":"kristheeya-keerthanangal","colName":"Kristheeya Keerthanangal"},{"n":397,"name":"Loke njan ","name2":"","col":"kristheeya-keerthanangal","colName":"Kristheeya Keerthanangal"},{"n":398,"name":"Kaathu Kaathu ","name2":"","col":"kristheeya-keerthanangal","colName":"Kristheeya Keerthanangal"},{"n":399,"name":"Bhagyanattil ","name2":"","col":"kristheeya-keerthanangal","colName":"Kristheeya Keerthanangal"},{"n":400,"name":"Namellarum ","name2":"","col":"kristheeya-keerthanangal","colName":"Kristheeya Keerthanangal"},{"n":401,"name":"Nin Sannidhiyil","name2":"","col":"kristheeya-keerthanangal","colName":"Kristheeya Keerthanangal"},{"n":402,"name":"Yeshuvae Nintae","name2":"","col":"kristheeya-keerthanangal","colName":"Kristheeya Keerthanangal"},{"n":403,"name":"Nin sannidhi mathy  ","name2":"","col":"kristheeya-keerthanangal","colName":"Kristheeya Keerthanangal"},{"n":404,"name":"En Priya ","name2":"","col":"kristheeya-keerthanangal","colName":"Kristheeya Keerthanangal"},{"n":405,"name":"Njan kartha  ","name2":"","col":"kristheeya-keerthanangal","colName":"Kristheeya Keerthanangal"},{"n":406,"name":"Dhaivahi Paithal  ","name2":"","col":"kristheeya-keerthanangal","colName":"Kristheeya Keerthanangal"},{"n":407,"name":"Sabhayakkekadisthanam","name2":"","col":"kristheeya-keerthanangal","colName":"Kristheeya Keerthanangal"},{"n":408,"name":"Yeshuvin thirusabhaye ","name2":"","col":"kristheeya-keerthanangal","colName":"Kristheeya Keerthanangal"},{"n":409,"name":"En asa yesuvil","name2":"","col":"kristheeya-keerthanangal","colName":"Kristheeya Keerthanangal"},{"n":410,"name":"Than Nithya Snehathal","name2":"","col":"kristheeya-keerthanangal","colName":"Kristheeya Keerthanangal"},{"n":411,"name":"Ente jeevan ","name2":"","col":"kristheeya-keerthanangal","colName":"Kristheeya Keerthanangal"},{"n":412,"name":"Aswasame","name2":"","col":"kristheeya-keerthanangal","colName":"Kristheeya Keerthanangal"},{"n":413,"name":"Daivathil Njan","name2":"","col":"kristheeya-keerthanangal","colName":"Kristheeya Keerthanangal"},{"n":414,"name":"Para Paramesha ","name2":"","col":"kristheeya-keerthanangal","colName":"Kristheeya Keerthanangal"},{"n":415,"name":"Yesuvae Thiru Namam Ethra","name2":"","col":"kristheeya-keerthanangal","colName":"Kristheeya Keerthanangal"},{"n":416,"name":"Enne rakshippan ","name2":"","col":"kristheeya-keerthanangal","colName":"Kristheeya Keerthanangal"},{"n":417,"name":"Daivamae Ee Andinae","name2":"","col":"kristheeya-keerthanangal","colName":"Kristheeya Keerthanangal"},{"n":418,"name":"inneram yeshu Devanae","name2":"","col":"kristheeya-keerthanangal","colName":"Kristheeya Keerthanangal"},{"n":419,"name":"Innayolam Thunachonae","name2":"","col":"kristheeya-keerthanangal","colName":"Kristheeya Keerthanangal"},{"n":420,"name":"Puthuvals ","name2":"","col":"kristheeya-keerthanangal","colName":"Kristheeya Keerthanangal"},{"n":421,"name":"Innu Namukeka ","name2":"","col":"kristheeya-keerthanangal","colName":"Kristheeya Keerthanangal"},{"n":422,"name":"Munnambara ","name2":"","col":"kristheeya-keerthanangal","colName":"Kristheeya Keerthanangal"},{"n":423,"name":"Mattin Thozhuthil","name2":"","col":"kristheeya-keerthanangal","colName":"Kristheeya Keerthanangal"},{"n":424,"name":"Karthanil aarthu  ","name2":"","col":"kristheeya-keerthanangal","colName":"Kristheeya Keerthanangal"},{"n":425,"name":"Christu Yesuvin Swathara","name2":"","col":"kristheeya-keerthanangal","colName":"Kristheeya Keerthanangal"},{"n":426,"name":"Kristhu Yesu ","name2":"","col":"kristheeya-keerthanangal","colName":"Kristheeya Keerthanangal"},{"n":427,"name":"Nithyanaya yahovaye","name2":"","col":"kristheeya-keerthanangal","colName":"Kristheeya Keerthanangal"},{"n":428,"name":"Rakshakantae divya","name2":"","col":"kristheeya-keerthanangal","colName":"Kristheeya Keerthanangal"},{"n":429,"name":"Varika Paraparane ","name2":"","col":"kristheeya-keerthanangal","colName":"Kristheeya Keerthanangal"},{"n":430,"name":"Alavilla Dhanagal","name2":"","col":"kristheeya-keerthanangal","colName":"Kristheeya Keerthanangal"},{"n":431,"name":"En Maname ","name2":"","col":"kristheeya-keerthanangal","colName":"Kristheeya Keerthanangal"},{"n":432,"name":"En Karthavae Nin","name2":"","col":"kristheeya-keerthanangal","colName":"Kristheeya Keerthanangal"},{"n":433,"name":"Sarvathin Rajanam","name2":"","col":"kristheeya-keerthanangal","colName":"Kristheeya Keerthanangal"},{"n":434,"name":"Nanniyal Ennullam","name2":"","col":"kristheeya-keerthanangal","colName":"Kristheeya Keerthanangal"},{"n":435,"name":"Nanniyode Njan ","name2":"","col":"kristheeya-keerthanangal","colName":"Kristheeya Keerthanangal"},{"n":436,"name":"Nin Dhanam Njan ","name2":"","col":"kristheeya-keerthanangal","colName":"Kristheeya Keerthanangal"},{"n":437,"name":"Uyarunnennullil ","name2":"","col":"kristheeya-keerthanangal","colName":"Kristheeya Keerthanangal"},{"n":438,"name":"Odikkodin Yeshuvodu","name2":"","col":"kristheeya-keerthanangal","colName":"Kristheeya Keerthanangal"},{"n":439,"name":"Daiva Kunjaditha","name2":"","col":"kristheeya-keerthanangal","colName":"Kristheeya Keerthanangal"},{"n":440,"name":"Nammudae Karthavam","name2":"","col":"kristheeya-keerthanangal","colName":"Kristheeya Keerthanangal"},{"n":441,"name":"Kalvary Krushil","name2":"","col":"kristheeya-keerthanangal","colName":"Kristheeya Keerthanangal"},{"n":442,"name":"Krushithanam Kristuve  ","name2":"","col":"kristheeya-keerthanangal","colName":"Kristheeya Keerthanangal"},{"n":443,"name":"Haleluyya Uyirtheshu","name2":"","col":"kristheeya-keerthanangal","colName":"Kristheeya Keerthanangal"},{"n":444,"name":"Adhwanikkunna Bharavahikalae","name2":"","col":"kristheeya-keerthanangal","colName":"Kristheeya Keerthanangal"},{"n":445,"name":"Innu Nee Orikkal Koodi","name2":"","col":"kristheeya-keerthanangal","colName":"Kristheeya Keerthanangal"},{"n":446,"name":"Maaridatha ","name2":"","col":"kristheeya-keerthanangal","colName":"Kristheeya Keerthanangal"},{"n":447,"name":"Sudhaatmaave ","name2":"","col":"kristheeya-keerthanangal","colName":"Kristheeya Keerthanangal"},{"n":448,"name":"Daivathintae Suvishasham","name2":"","col":"kristheeya-keerthanangal","colName":"Kristheeya Keerthanangal"},{"n":449,"name":"Daivathin Puthranam","name2":"","col":"kristheeya-keerthanangal","colName":"Kristheeya Keerthanangal"},{"n":450,"name":"Manasa Modhaka","name2":"","col":"kristheeya-keerthanangal","colName":"Kristheeya Keerthanangal"},{"n":451,"name":"Dhaivame Nin Dhayayal ","name2":"","col":"kristheeya-keerthanangal","colName":"Kristheeya Keerthanangal"},{"n":452,"name":"Yeshuvae Raksha Dayaka","name2":"","col":"kristheeya-keerthanangal","colName":"Kristheeya Keerthanangal"},{"n":453,"name":"Thirukkarathal","name2":"","col":"kristheeya-keerthanangal","colName":"Kristheeya Keerthanangal"},{"n":454,"name":"Arpikunne","name2":"","col":"kristheeya-keerthanangal","colName":"Kristheeya Keerthanangal"},{"n":455,"name":"Enikkalla njan ","name2":"","col":"kristheeya-keerthanangal","colName":"Kristheeya Keerthanangal"},{"n":456,"name":"Papikalae Rakshichiduvan","name2":"","col":"kristheeya-keerthanangal","colName":"Kristheeya Keerthanangal"},{"n":457,"name":"Nadhi Thullyam","name2":"","col":"kristheeya-keerthanangal","colName":"Kristheeya Keerthanangal"},{"n":458,"name":"Pedi Venda Lasham","name2":"","col":"kristheeya-keerthanangal","colName":"Kristheeya Keerthanangal"},{"n":459,"name":"Bholokaam Vanatharathiludae","name2":"","col":"kristheeya-keerthanangal","colName":"Kristheeya Keerthanangal"},{"n":460,"name":"Papikkayullorurava","name2":"","col":"kristheeya-keerthanangal","colName":"Kristheeya Keerthanangal"},{"n":461,"name":"Yeshu Nadha Poorna","name2":"","col":"kristheeya-keerthanangal","colName":"Kristheeya Keerthanangal"},{"n":462,"name":"En Idayan ","name2":"","col":"kristheeya-keerthanangal","colName":"Kristheeya Keerthanangal"},{"n":463,"name":"Karthan Thanna Nal","name2":"","col":"kristheeya-keerthanangal","colName":"Kristheeya Keerthanangal"},{"n":464,"name":"Nallidayanam Yeshu","name2":"","col":"kristheeya-keerthanangal","colName":"Kristheeya Keerthanangal"},{"n":465,"name":"Yahu Nalla Idayan","name2":"","col":"kristheeya-keerthanangal","colName":"Kristheeya Keerthanangal"},{"n":466,"name":"Ashwasa Dayakanai","name2":"","col":"kristheeya-keerthanangal","colName":"Kristheeya Keerthanangal"},{"n":467,"name":"Nanmayallathonnum ","name2":"","col":"kristheeya-keerthanangal","colName":"Kristheeya Keerthanangal"},{"n":468,"name":"Man Neerthodinay ","name2":"","col":"kristheeya-keerthanangal","colName":"Kristheeya Keerthanangal"},{"n":469,"name":"Ennenikken ","name2":"","col":"kristheeya-keerthanangal","colName":"Kristheeya Keerthanangal"},{"n":470,"name":"En Priya Rekshakane ","name2":"","col":"kristheeya-keerthanangal","colName":"Kristheeya Keerthanangal"},{"n":471,"name":"Karthave Nin Roopam ","name2":"","col":"kristheeya-keerthanangal","colName":"Kristheeya Keerthanangal"},{"n":472,"name":"Ithu Varae ennae","name2":"","col":"kristheeya-keerthanangal","colName":"Kristheeya Keerthanangal"},{"n":473,"name":"Enne Shakthanakidunnavan ","name2":"","col":"kristheeya-keerthanangal","colName":"Kristheeya Keerthanangal"},{"n":474,"name":"Viswasthan En Dhaivam ","name2":"","col":"kristheeya-keerthanangal","colName":"Kristheeya Keerthanangal"},{"n":475,"name":"Daivam Sakalavum ","name2":"","col":"kristheeya-keerthanangal","colName":"Kristheeya Keerthanangal"},{"n":476,"name":"Senayin Adhipan ","name2":"","col":"kristheeya-keerthanangal","colName":"Kristheeya Keerthanangal"},{"n":477,"name":"Venam Ninnae","name2":"","col":"kristheeya-keerthanangal","colName":"Kristheeya Keerthanangal"},{"n":478,"name":"Ee lokathil Nam","name2":"","col":"kristheeya-keerthanangal","colName":"Kristheeya Keerthanangal"},{"n":479,"name":"O Chinthikkamel","name2":"","col":"kristheeya-keerthanangal","colName":"Kristheeya Keerthanangal"},{"n":480,"name":"Muttum Vedippakkan","name2":"","col":"kristheeya-keerthanangal","colName":"Kristheeya Keerthanangal"},{"n":481,"name":"Karthavarulunnu ","name2":"","col":"kristheeya-keerthanangal","colName":"Kristheeya Keerthanangal"},{"n":482,"name":"Nin thiru raktham","name2":"","col":"kristheeya-keerthanangal","colName":"Kristheeya Keerthanangal"},{"n":483,"name":"En Daivamae Nin","name2":"","col":"kristheeya-keerthanangal","colName":"Kristheeya Keerthanangal"},{"n":484,"name":"Hae Dahikkunnavar","name2":"","col":"kristheeya-keerthanangal","colName":"Kristheeya Keerthanangal"},{"n":485,"name":"Nurukapetta Nadha ","name2":"","col":"kristheeya-keerthanangal","colName":"Kristheeya Keerthanangal"},{"n":486,"name":"Njanayogyan ","name2":"","col":"kristheeya-keerthanangal","colName":"Kristheeya Keerthanangal"},{"n":487,"name":"Nallavanae Nal Vazhikattie","name2":"","col":"kristheeya-keerthanangal","colName":"Kristheeya Keerthanangal"},{"n":488,"name":"Yeshuvepolundo ","name2":"","col":"kristheeya-keerthanangal","colName":"Kristheeya Keerthanangal"},{"n":489,"name":"Cherum Yesuvil  ","name2":"","col":"kristheeya-keerthanangal","colName":"Kristheeya Keerthanangal"},{"n":490,"name":"Ithratholamenne ","name2":"","col":"kristheeya-keerthanangal","colName":"Kristheeya Keerthanangal"},{"n":491,"name":"Njanum Enikulla ","name2":"","col":"kristheeya-keerthanangal","colName":"Kristheeya Keerthanangal"},{"n":492,"name":"Krupa Manoharam","name2":"","col":"kristheeya-keerthanangal","colName":"Kristheeya Keerthanangal"},{"n":493,"name":"Christhu Namam","name2":"","col":"kristheeya-keerthanangal","colName":"Kristheeya Keerthanangal"},{"n":494,"name":"Nithyamam Prakashame ","name2":"","col":"kristheeya-keerthanangal","colName":"Kristheeya Keerthanangal"},{"n":495,"name":"Nin Karunakal Karthavae","name2":"","col":"kristheeya-keerthanangal","colName":"Kristheeya Keerthanangal"},{"n":496,"name":"En Priyantae Swaram","name2":"","col":"kristheeya-keerthanangal","colName":"Kristheeya Keerthanangal"},{"n":497,"name":"Shamippan Nilathil","name2":"","col":"kristheeya-keerthanangal","colName":"Kristheeya Keerthanangal"},{"n":498,"name":"Ethra Sawbhagiyamae","name2":"","col":"kristheeya-keerthanangal","colName":"Kristheeya Keerthanangal"},{"n":499,"name":"Paapapaashathal ","name2":"","col":"kristheeya-keerthanangal","colName":"Kristheeya Keerthanangal"},{"n":500,"name":"En Yesu Than  ","name2":"","col":"kristheeya-keerthanangal","colName":"Kristheeya Keerthanangal"},{"n":501,"name":"Pakarenam Nin Athmave ","name2":"","col":"kristheeya-keerthanangal","colName":"Kristheeya Keerthanangal"},{"n":502,"name":"Ezhunzrulka Dhaivame ","name2":"","col":"kristheeya-keerthanangal","colName":"Kristheeya Keerthanangal"},{"n":503,"name":"Innu Theerum Varshathil","name2":"","col":"kristheeya-keerthanangal","colName":"Kristheeya Keerthanangal"},{"n":504,"name":"Palaram Nammal ","name2":"","col":"kristheeya-keerthanangal","colName":"Kristheeya Keerthanangal"},{"n":"DOX-I","name":"ENNEKKUM MAHATHVAM | DOXOLOGY","name2":"എന്നേക്കും മഹത്വം","col":"kristheeya-keerthanangal","colName":"Kristheeya Keerthanangal"},{"n":"DOX-II","name":"SARVVA BUDHIYUM | DOXOLOGY ","name2":"സര്‍വ്വ ബുദ്ധിയും","col":"kristheeya-keerthanangal","colName":"Kristheeya Keerthanangal"},{"n":"DOX-III","name":"Sthuthi Ennennum Paadidum | DOXOLOGY ","name2":"സ്തുതി എന്നെന്നും പാടിടും","col":"kristheeya-keerthanangal","colName":"Kristheeya Keerthanangal"},{"n":"DOX-IV","name":"DAIVAME ANUGRAHIKKA | DOXOLOGY","name2":"ദൈവമേ അനുഗ്രഹിക്ക","col":"kristheeya-keerthanangal","colName":"Kristheeya Keerthanangal"},{"n":"DOX-V","name":"Daivame Nin Snehathode | DOXOLOGY ","name2":"ദൈവമേ നിന്‍ സ്നേഹത്തോടെ","col":"kristheeya-keerthanangal","colName":"Kristheeya Keerthanangal"},{"n":"DOX-VI","name":"DHAIVAME AYAYKKA | DOXOLOGY ","name2":"ദൈവമേ അയയ്ക്ക","col":"kristheeya-keerthanangal","colName":"Kristheeya Keerthanangal"},{"n":"DOX-VII","name":"Yeshuvin Kripaakadaaksham | DOXOLOGY ","name2":"യേശുവിന്‍ കൃപാകടാക്ഷം","col":"kristheeya-keerthanangal","colName":"Kristheeya Keerthanangal"},{"n":"DOX-VIII","name":"SARVVASHISHATHIN THATHANE | DOXOLOGY ","name2":"സര്‍വ്വാശിഷത്തില്‍ താതനെ","col":"kristheeya-keerthanangal","colName":"Kristheeya Keerthanangal"},{"n":"DOX-IX","name":"Pithruputhraatmanam | DOXOLOGY","name2":"പിതൃപുത്രാത്മനാം","col":"kristheeya-keerthanangal","colName":"Kristheeya Keerthanangal"},{"n":"DOX-X","name":"Anugrahathode Ippol | DOXOLOGY ","name2":"അനുഗ്രഹത്തോടെ ഇപ്പോൾ (329)","col":"kristheeya-keerthanangal","colName":"Kristheeya Keerthanangal"},{"n":"DOX-XI","name":"Kaanum Vare Ini | DOXOLOGY ","name2":"കാണുമ്പോള്‍ വരെ ഇനി (328)","col":"kristheeya-keerthanangal","colName":"Kristheeya Keerthanangal"},{"n":"DOX-XII","name":"Nithyanaaya Yahovaaye | DOXOLOGY ","name2":"നിത്യനായ യഹോവായേ (427)","col":"kristheeya-keerthanangal","colName":"Kristheeya Keerthanangal"},{"n":"DOX-XIII","name":"Rakshakante | DOXOLOGY ","name2":"രക്ഷകന്റെ (428)","col":"kristheeya-keerthanangal","colName":"Kristheeya Keerthanangal"},{"n":18,"name":"YAHE NINTE NAAMAM","name2":"യഹേ നിന്റെ നാമം","col":"maramon-2013","colName":"Maramon Convention 2013"},{"n":19,"name":"STHOTHRAM PAADEEDUKA","name2":"സ്തോത്രം പാടീടുക","col":"maramon-2013","colName":"Maramon Convention 2013"},{"n":27,"name":"NAYANANGAL NIRAYUM","name2":"നയനങ്ങൾ നിറയും","col":"maramon-2013","colName":"Maramon Convention 2013"},{"n":28,"name":"THARALITHAMAYORU","name2":"തരളിതമായൊരു","col":"maramon-2013","colName":"Maramon Convention 2013"},{"n":29,"name":"KAARUNNYAVAANE","name2":"കാരുണ്യവാനെ","col":"maramon-2013","colName":"Maramon Convention 2013"},{"n":35,"name":"KARUNA NIRANJAVANE","name2":"കരുണ നിറഞ്ഞവനെ","col":"maramon-2013","colName":"Maramon Convention 2013"},{"n":36,"name":"DHAIVAME NANNIYAL","name2":"ദൈവമെ നന്നിയാൽ","col":"maramon-2013","colName":"Maramon Convention 2013"},{"n":42,"name":"ANUNIMISHAM","name2":"അനുനിമിഷം","col":"maramon-2013","colName":"Maramon Convention 2013"},{"n":43,"name":"KRIPAMATHIYE","name2":"ക്രിപമതിയെ","col":"maramon-2013","colName":"Maramon Convention 2013"},{"n":44,"name":"YAHOVA EN","name2":"യഹോവയെൻ","col":"maramon-2013","colName":"Maramon Convention 2013"},{"n":55,"name":"ITHANAALUM NJAAN","name2":"ഇത്രനാളും ഞാൻ","col":"maramon-2013","colName":"Maramon Convention 2013"},{"n":66,"name":"VACHANAM THIRUVACHANAM","name2":"വചനം തിരുവചനം","col":"maramon-2013","colName":"Maramon Convention 2013"},{"n":75,"name":"AATHMA PHALANGALAL","name2":"അത്മ ഫലങ്ങളാൽ","col":"maramon-2013","colName":"Maramon Convention 2013"},{"n":90,"name":"BELAHEENATHAYIL","name2":"ബേലഹീനതയിൽ","col":"maramon-2013","colName":"Maramon Convention 2013"},{"n":91,"name":"KANNUNEER KANNUNNA","name2":"കണ്ണുനീർ കാണുന്ന","col":"maramon-2013","colName":"Maramon Convention 2013"},{"n":92,"name":"ANTHYATHOLAM","name2":"അന്ത്യത്തോളം","col":"maramon-2013","colName":"Maramon Convention 2013"},{"n":1,"name":"THREYEKA DAIVAME VISHUDHA AATHMAVE","name2":"ത്രിയേക ദൈവമേ വിശുദ്ധാത്മാവേ","col":"maramon-2021","colName":"Maramon Convention 2021"},{"n":2,"name":"KARUTHUNNEN NADHAN THIRUKKARATHAAL","name2":"കരുതുന്നെൻ നാഥൻ തിരുക്കരതാൽ","col":"maramon-2021","colName":"Maramon Convention 2021"},{"n":3,"name":"YESHUVIN SNEHAM NITHYAM RUCHICHU","name2":"യേശുവിൻ സ്നേഹം നിത്യം രുചിച്ചു","col":"maramon-2021","colName":"Maramon Convention 2021"},{"n":4,"name":"INNAYOLAM THIRUSABHAYE","name2":"ഇന്നയോളം തിരുസഭയേ","col":"maramon-2021","colName":"Maramon Convention 2021"},{"n":5,"name":"YESHUVE POLENNE SNEHICHIDAAN","name2":"യേശുവേ പോലെന്നെ","col":"maramon-2021","colName":"Maramon Convention 2021"},{"n":6,"name":"NOVUKAL NIRAYUM","name2":"നോവുകൾ നിറയും","col":"maramon-2021","colName":"Maramon Convention 2021"},{"n":7,"name":"KARUTHALIN KARANGALAL","name2":"കരുതലിൻ കരങ്ങളാൽ","col":"maramon-2021","colName":"Maramon Convention 2021"},{"n":8,"name":"PUTHIYORU GEETHAMENNIL","name2":"പുതിയൊരു ഗീതമെന്നിൽ","col":"maramon-2021","colName":"Maramon Convention 2021"},{"n":9,"name":"AKALARUTHE NADHA","name2":"അകലരുതേ നാഥാ എൻ പ്രാർത്ഥന","col":"maramon-2021","colName":"Maramon Convention 2021"},{"n":10,"name":"PUTHIYORU GEETHAMENNIL...","name2":"പുതിയൊരു ഗീതമെന്നിൽ","col":"maramon-2021","colName":"Maramon Convention 2021"},{"n":11,"name":"KARUTHUNNEN NADHAN","name2":"കരുതുന്നെൻ നാഥൻ","col":"maramon-2021","colName":"Maramon Convention 2021"},{"n":12,"name":"YESHUVIN SNEHAM","name2":"യേശുവിൻ സ്നേഹം","col":"maramon-2021","colName":"Maramon Convention 2021"},{"n":13,"name":"INNAYOLAM THIRUSABHAYE","name2":"ഇന്നയോളം തിരുസഭയേ","col":"maramon-2021","colName":"Maramon Convention 2021"},{"n":14,"name":"THALARATHE MANAME","name2":"തളരാതെ മനമേ,  കൂടെയുണ്ടെന്നും","col":"maramon-2021","colName":"Maramon Convention 2021"},{"n":15,"name":" KARUTHALIN KARANGALAL","name2":"കരുതലിൻ കരങ്ങളാൽ","col":"maramon-2021","colName":"Maramon Convention 2021"},{"n":16,"name":" YESHUVE POLENNE SNEHICHIDAAN","name2":"യേശുവേ പോലെന്നെ","col":"maramon-2021","colName":"Maramon Convention 2021"},{"n":17,"name":"NOVUKAL NIRAYUM","name2":"നോവുകൾ നിറയും","col":"maramon-2021","colName":"Maramon Convention 2021"},{"n":18,"name":"THREEYEKA DAIVAME VISUDHA","name2":"ത്രിയേക ദൈവമേ വിശുദ്ധ ആത്മാവേ","col":"maramon-2021","colName":"Maramon Convention 2021"},{"n":19,"name":"AKALARUTHE. NADHA","name2":"അകലരുതേ നാഥാ എൻ പ്രാർത്ഥന","col":"maramon-2021","colName":"Maramon Convention 2021"},{"n":20,"name":"THALARATHE MANAME","name2":"തളരാതെ മനമേ","col":"maramon-2021","colName":"Maramon Convention 2021"},{"n":9,"name":"NANMMAKALENNUM","name2":"നന്മകളെന്നും","col":"maramon-2023","colName":"Maramon Convention 2023"},{"n":23,"name":"THAMASSE","name2":"തമസ്സെ","col":"maramon-2023","colName":"Maramon Convention 2023"},{"n":28,"name":"PRIYANORUVANUNDENIKE","name2":"പ്രിയനോരുവനുണ്ടെനിക്കെ","col":"maramon-2023","colName":"Maramon Convention 2023"},{"n":40,"name":"MANAMURUKI PRARTHICHIDAM","name2":"മനമുരുകി പ്രാർത്ഥിച്ചിടം","col":"maramon-2023","colName":"Maramon Convention 2023"},{"n":45,"name":"VACHANAM SATHYAVACHANAM","name2":"വചനം സത്യവചനം","col":"maramon-2023","colName":"Maramon Convention 2023"},{"n":50,"name":"EZHUNELKKAM NAAM","name2":"എഴുന്നേൽക്കാം നാം","col":"maramon-2023","colName":"Maramon Convention 2023"},{"n":56,"name":"NJAANUM KUDUMBAVUM","name2":"ഞാനും കുടുംബവും","col":"maramon-2023","colName":"Maramon Convention 2023"},{"n":57,"name":"PARKUM NAATHANODU KOODE","name2":"പാർക്കും നാഥനോടു കൂടെ","col":"maramon-2023","colName":"Maramon Convention 2023"},{"n":68,"name":"YESHU ENTE NALLA SNEHITHAN","name2":"യേശു എന്റെ നല്ല സ്നേഹിതൻ","col":"maramon-2023","colName":"Maramon Convention 2023"},{"n":75,"name":"ORO RAAVUM ORO PAKALUM","name2":"ഓരോ രാവും ഓരോ പകലും","col":"maramon-2023","colName":"Maramon Convention 2023"},{"n":89,"name":"ENTE KANNUNEER KAANUNNA DAIVAME","name2":"എന്റെ കണ്ണുനീർ കാണുന്ന ദൈവമേ","col":"maramon-2023","colName":"Maramon Convention 2023"},{"n":96,"name":"MALPRIYAN YESHUVARARAYI","name2":"മൽപ്രിയൻ യേശുവരാറായി","col":"maramon-2023","colName":"Maramon Convention 2023"},{"n":16,"name":"NANDIYALLATHONNUM","name2":"നന്ദിയല്ലാതൊന്നും","col":"maramon-2024","colName":"Maramon Convention 2024"},{"n":30,"name":"KRIPAYAAL KRIPAYAAL ","name2":"ക്രിപയാൽ ക്രിപയാൽ","col":"maramon-2024","colName":"Maramon Convention 2024"},{"n":31,"name":"PAAPAMILLA YESHUVINTE RAKTHAM ","name2":"പാപമില്ല യേശുവിന്റെ രക്തം","col":"maramon-2024","colName":"Maramon Convention 2024"},{"n":40,"name":"ANUGRAHAMAZHAYAAI ","name2":"അനുഗ്രഹമഴയായി","col":"maramon-2024","colName":"Maramon Convention 2024"},{"n":43,"name":"VACHANAM ATHIMADHURAM ","name2":"വചനം അതിമധുരം","col":"maramon-2024","colName":"Maramon Convention 2024"},{"n":44,"name":"THIRUVACHANAM NAL ","name2":"തിരുവചനം നല്‍","col":"maramon-2024","colName":"Maramon Convention 2024"},{"n":48,"name":"NADATHIDUM VAZHIKAL ","name2":"നടത്തിടും വഴികൾ","col":"maramon-2024","colName":"Maramon Convention 2024"},{"n":59,"name":"EDAYANAAI KOOTTIRUNNU ","name2":"ഇടയനായ് കൂട്ടിരുന്നു","col":"maramon-2024","colName":"Maramon Convention 2024"},{"n":62,"name":"ENNE KARUTHAAN ","name2":"എന്നെ കരുതാൻ","col":"maramon-2024","colName":"Maramon Convention 2024"},{"n":63,"name":"PRATHYAASHA PAKARUNNA ","name2":"പ്രത്യാശ പകരുന്ന","col":"maramon-2024","colName":"Maramon Convention 2024"},{"n":64,"name":"YESHUVIN KRIPAKAL","name2":"യേശുവിൻ കൃപകൾ","col":"maramon-2024","colName":"Maramon Convention 2024"},{"n":67,"name":"VAZHIYUM VAATHILUM ","name2":"വഴിയും വാതിലും","col":"maramon-2024","colName":"Maramon Convention 2024"},{"n":70,"name":"NADATHIYA VIDHANGAL ","name2":"നടതിയ വിധങ്ങൾ","col":"maramon-2024","colName":"Maramon Convention 2024"},{"n":75,"name":"DAIVATHIL VISHVASIKKA ","name2":"ദൈവത്തില്‍ വിശ്വസിക്ക","col":"maramon-2024","colName":"Maramon Convention 2024"},{"n":92,"name":"KARUNAMAYANE","name2":"കരുണാമയനെ","col":"maramon-2024","colName":"Maramon Convention 2024"},{"n":95,"name":"KAARUNAYA VARIDHE KANIYENAME","name2":"കാരുണ്യ വരിധേ കനിയേണമേ","col":"maramon-2024","colName":"Maramon Convention 2024"},{"n":7,"name":"Sankeerthanangal","name2":"സങ്കീർത്തനങ്ങൾ","col":"maramon-2025","colName":"Maramon Convention 2025"},{"n":24,"name":"Ithranaalum Nashtamaakki","name2":"ഇത്രനാളും നഷ്ടമാക്കി","col":"maramon-2025","colName":"Maramon Convention 2025"},{"n":33,"name":"Ente Naathan Ente Priyan","name2":"എന്റെ നാഥൻ എന്റെ പ്രിയൻ","col":"maramon-2025","colName":"Maramon Convention 2025"},{"n":34,"name":"Enne Ariyunnoru Naathan","name2":"എന്നെ അറിയുന്നൊരു നാഥൻ","col":"maramon-2025","colName":"Maramon Convention 2025"},{"n":48,"name":"Randu Kaashitta Vidhavaye","name2":"രണ്ട് കാശിട്ട വിധവയെ","col":"maramon-2025","colName":"Maramon Convention 2025"},{"n":57,"name":"Hrydayam Nurungiyorkku","name2":"ഹൃദയം നുറുങ്ങിയോർക്ക്","col":"maramon-2025","colName":"Maramon Convention 2025"},{"n":58,"name":"Karayumbol Pokaanoridamundu","name2":"കരയുമ്പോൾ പോകാനൊരിടമുണ്ട്","col":"maramon-2025","colName":"Maramon Convention 2025"},{"n":66,"name":"Koithukaalam","name2":"കൊയ്തുകാലം","col":"maramon-2025","colName":"Maramon Convention 2025"},{"n":67,"name":"Vinnilente Veedorukki","name2":"വിണ്ണിലെന്റെ വീടോരുക്കി","col":"maramon-2025","colName":"Maramon Convention 2025"},{"n":72,"name":"Yeshu Orunaal","name2":"യേശു ഒരുനാൾ","col":"maramon-2025","colName":"Maramon Convention 2025"},{"n":73,"name":"Imbamulloru Kudumbamaavaan","name2":"ഇമ്പമുള്ളൊരു കുടുംബമാവാൻ","col":"maramon-2025","colName":"Maramon Convention 2025"},{"n":77,"name":"Aakulangaleri","name2":"ആകുലങ്ങളേറി","col":"maramon-2025","colName":"Maramon Convention 2025"},{"n":85,"name":"Thingum Hrudayabhaarangalumaay","name2":"തിങ്ങും ഹൃദയഭാരങ്ങളുമായ്","col":"maramon-2025","colName":"Maramon Convention 2025"},{"n":86,"name":"Nimisham Mathi Oru Nimisham Mathi","name2":"നിമിഷം മതി ഒരു നിമിഷം മതി","col":"maramon-2025","colName":"Maramon Convention 2025"},{"n":87,"name":"Kalangenden Maname","name2":"കലങ്ങേണ്ടെൻ മനമെ","col":"maramon-2025","colName":"Maramon Convention 2025"},{"n":93,"name":"Karuthunna Daivam","name2":"കരുതുന്ന ദൈവം","col":"maramon-2025","colName":"Maramon Convention 2025"},{"n":12,"name":"Daivame Nee Ennum","name2":"ദൈവമേ നീ എന്നും","col":"maramon-2026","colName":"Maramon Convention 2026"},{"n":13,"name":"Krupayude Thanalil","name2":"കൃപയുടെ തണലിൽ","col":"maramon-2026","colName":"Maramon Convention 2026"},{"n":30,"name":"Kaanatha Kaaryathinte","name2":"കാണാത്ത കാര്യത്തിന്റേ","col":"maramon-2026","colName":"Maramon Convention 2026"},{"n":31,"name":"Oru Vaakku Kalpichaal","name2":"ഒരു വാക്കു കല്പിച്ചാൽ","col":"maramon-2026","colName":"Maramon Convention 2026"},{"n":46,"name":"Kashtamente Jeevithathil","name2":"കഷ്ടമെന്റെ ജീവിതത്തിൽ","col":"maramon-2026","colName":"Maramon Convention 2026"},{"n":72,"name":"Naathaa Nin Thiruvishtam","name2":"നാഥാ നിൻ തിരുവിഷ്ടം","col":"maramon-2026","colName":"Maramon Convention 2026"},{"n":75,"name":"Ithratholam Enne Pottippularthiya","name2":"ഇത്രത്തോളം എന്നെ പോറ്റിപ്പുലർത്തിയ","col":"maramon-2026","colName":"Maramon Convention 2026"},{"n":76,"name":"Karuthunna Karthan","name2":"കരുതുന്ന കർത്തൻ","col":"maramon-2026","colName":"Maramon Convention 2026"},{"n":79,"name":"Niranjuthulumbum Sneham","name2":"നിറഞ്ഞു തുളുമ്പും സ്നേഹം","col":"maramon-2026","colName":"Maramon Convention 2026"},{"n":80,"name":"Ennethedi Vanna","name2":"എന്നെതേടി വന്ന","col":"maramon-2026","colName":"Maramon Convention 2026"},{"n":81,"name":"Karunayin Urava Thurannu","name2":"കരുണയിൻ ഉറവ തുറന്നു","col":"maramon-2026","colName":"Maramon Convention 2026"},{"n":89,"name":"Swarga Naathan","name2":"സ്വർഗ്ഗ നാഥൻ","col":"maramon-2026","colName":"Maramon Convention 2026"},{"n":90,"name":"Srushtaavaakum Daivame","name2":"സൃഷ്ടാവാകും ദൈവമേ","col":"maramon-2026","colName":"Maramon Convention 2026"},{"n":91,"name":"Naatha Nin Naamam","name2":"നാഥ നിൻ നാമം","col":"maramon-2026","colName":"Maramon Convention 2026"},{"n":92,"name":"Karuthuvaan Njaanillayo","name2":"കരുതുവാൻ ഞാൻ ഇല്ലായ്ക്ക്","col":"maramon-2026","colName":"Maramon Convention 2026"},{"n":93,"name":"Parishudhaathmaavin Falangal","name2":"പരിശുദ്ധാത്മാവിൻ ഫലങ്ങൾ","col":"maramon-2026","colName":"Maramon Convention 2026"},{"n":"PW1","name":"MASHIHAYEKANMAN","name2":"മശിഹായെ കാണ്മാൻ","col":"passion-week","colName":"Passion Week"},{"n":"PW2","name":"NADHA NADHA","name2":"നാഥാ നാഥാ","col":"passion-week","colName":"Passion Week"},{"n":"PW3","name":"DEVA PARAMESHA","name2":"ദേവാ പരമേശാ","col":"passion-week","colName":"Passion Week"},{"n":"PW4","name":"AARIDATHIL POKENDU","name2":"ആരിടത്തിൽ പോകേണ്ടു","col":"passion-week","colName":"Passion Week"},{"n":"PW5","name":"NJANGALKKAY ETTANIN","name2":"ഞങ്ങൾക്കായ് ഏറ്റ നിൻ","col":"passion-week","colName":"Passion Week"},{"n":"PW6","name":"KASHTATHA SKEEPPA","name2":"കഴ്ടത സ്കീപ്പ","col":"passion-week","colName":"Passion Week"},{"n":"PW7","name":"THAN DHIVYA BALIYAL","name2":"തൻ ദീവ്യ ബലിയാൽ","col":"passion-week","colName":"Passion Week"},{"n":"PW8","name":"NJANGALKKAYATHI KASHTATHAKAL","name2":"ഞങ്ങൾക്കായതി കഴ്ടതകൾ","col":"passion-week","colName":"Passion Week"},{"n":"PW9","name":"VANAM BHOOMI","name2":"വാനം ഭൂമി","col":"passion-week","colName":"Passion Week"},{"n":"PW10","name":"NINNE VIDHICHORE","name2":"നിന്നെ വിധിച്ചോരെ","col":"passion-week","colName":"Passion Week"},{"n":"PW11","name":"INNALIL YOODHAR","name2":"ഇന്നാളിൽ യൂദർ","col":"passion-week","colName":"Passion Week"},{"n":"PW12","name":"SWARBHOOLOKANGAL ASAKALAM","name2":"സ്വർഭൂലോകങ്ങൾ ആസകലം","col":"passion-week","colName":"Passion Week"},{"n":"PW13","name":"MANASUTHANAYORU DHAIVASUTHAN","name2":"മനുസുതനായോരു ദൈവസുതൻ","col":"passion-week","colName":"Passion Week"},{"n":"PW14","name":"LOKARAKSHAKKAI","name2":"ലോകരക്ഷക്കായി","col":"passion-week","colName":"Passion Week"},{"n":"PW15","name":"AARAMNAAL ATHIRAVILE","name2":"ആറാംനാൾ അതിരവിലെ","col":"passion-week","colName":"Passion Week"},{"n":"PW16","name":"AARAMNAAL MAYYAYILESHU","name2":"ആറാംനാൾ മയ്യയിലേശു","col":"passion-week","colName":"Passion Week"},{"n":"PW17","name":"NEETHIMAN MAUNAMODE","name2":"നീതിമാൻ മൌനമോടെ","col":"passion-week","colName":"Passion Week"},{"n":"PW18","name":"ALBHUTHAMADAYALAM","name2":"അൽഭൂതമടയാളം","col":"passion-week","colName":"Passion Week"},{"n":"PW19","name":"NASHALOKHATHE KANDAVAN","name2":"നാശലോകത്തെ കണ്ടവൻ","col":"passion-week","colName":"Passion Week"},{"n":"PW20","name":"NILAVILI NJAN KELKKUNNE","name2":"നിലവിളി ഞാൻ കേൾക്കുന്നേ","col":"passion-week","colName":"Passion Week"},{"n":"PW21","name":"HE PAPI NINAKUNDAYA","name2":"ഹെ പാപി നിനക്കുണ്ടയ","col":"passion-week","colName":"Passion Week"},{"n":"PW22","name":"ELLA DIVASANGALIL","name2":"എല്ലാ ദിവസങ്ങളിൽ","col":"passion-week","colName":"Passion Week"},{"n":"PW23","name":"DEVA JATHANE NIN UYARPPAL","name2":"ദേവജാതനെ നിന്റെ ഉയർപ്പാൽ","col":"passion-week","colName":"Passion Week"},{"n":"HC1","name":"NALLAVANUM NJYANIYUMAYULLA","name2":"നല്ലവനും ഞാനിയുമായുള്ള | Page 105","col":"holy-communion","colName":"Holy Communion"},{"n":"HC2","name":"NEETHI PUNYAM","name2":"നീതി പുണ്യം | Page 105","col":"holy-communion","colName":"Holy Communion"},{"n":"HC3","name":"RAHASYAM RAHASYAM","name2":"രഹസ്യം രഹസ്യം | Page 100","col":"holy-communion","colName":"Holy Communion"},{"n":"HC4","name":"STHUTHIPPIN STHUTHIPPIN","name2":"സ്തുതിപ്പിൻ സ്തുതിപ്പിൻ | Page 99","col":"holy-communion","colName":"Holy Communion"},{"n":"HC5","name":"KRISTHESHU NIN KURISHALUM","name2":"ക്രിസ്തേശു നിൻ കുരിശാലും | Page 99","col":"holy-communion","colName":"Holy Communion"},{"n":"HC6","name":"ATHYUNNATHANGALIL VASAM","name2":"അത്യുന്നതങ്ങളിൽ വാസം | Page 97","col":"holy-communion","colName":"Holy Communion"},{"n":"HC7","name":"NJANGALKKULLA KARTHAVE","name2":"ഞങ്ങൾക്കുള്ള കർത്താവേ | Page 97","col":"holy-communion","colName":"Holy Communion"},{"n":"HC8","name":"  KARTHAVE NIN VALABHAGATHIN","name2":"കർത്താവേ നിൻ വലഭാഗത്തിൻ | Page 94","col":"holy-communion","colName":"Holy Communion"},{"n":"HC9","name":" NIN SHARANATHIL ","name2":"നിൻ ശരണത്തിൽ | Page 93","col":"holy-communion","colName":"Holy Communion"},{"n":"HC10","name":" KARTHAVE KANINJEEDANE","name2":"കർത്താവേ കനിഞ്ഞീടണമേ | Page 92","col":"holy-communion","colName":"Holy Communion"},{"n":"HC11","name":" DAIVASUTHAR NAM ","name2":"ദൈവസുതർ നാം | Page 92","col":"holy-communion","colName":"Holy Communion"},{"n":"HC12","name":" GUNAVANE NIN VATHILIL","name2":"ഗുണവനേ നിൻ വാതിലിൽ | Page 86","col":"holy-communion","colName":"Holy Communion"},{"n":"HC13","name":" ARDRAMATHE NIN VATHILIL","name2":"അത്യുന്നതങ്ങളിൽ വാസം | Page 97","col":"holy-communion","colName":"Holy Communion"},{"n":"HC14","name":" VANAM BHOOMI","name2":"വാനം ഭൂമി | Page 81","col":"holy-communion","colName":"Holy Communion"},{"n":"HC15","name":" KARTHAVE NIN DHASARAM","name2":"കർത്താവേ നിൻ ദാസരാം | Page 79","col":"holy-communion","colName":"Holy Communion"},{"n":"HC16","name":"KARTHAVE NIN VATHILIL","name2":"കർത്താവേ നിൻ വാതിലിൽ | Page 79","col":"holy-communion","colName":"Holy Communion"},{"n":"HC17","name":"KARTHAVE NINNOD","name2":"കർത്താവേ നിന്നോട് | Page 76","col":"holy-communion","colName":"Holy Communion"},{"n":"HC18","name":"DAIVATHIN SUVISHESHAM","name2":"ദൈവത്തിൻ സുവിശേഷം | Page 74","col":"holy-communion","colName":"Holy Communion"},{"n":"HC19","name":" PAULOSE SLEEHA","name2":"പൗലോസ് ശ്ലീഹ | Page 73","col":"holy-communion","colName":"Holy Communion"},{"n":"HC20","name":"AHARON ANACHA","name2":"അഹറോൺ അണച്ച | Page 70","col":"holy-communion","colName":"Holy Communion"},{"n":"HC21","name":"PAPIKALIL KRUPA","name2":"പാപികളിൽ കൃപ | Page 70","col":"holy-communion","colName":"Holy Communion"},{"n":"HC22","name":"KARTHAVE NIN","name2":"കർത്താവേ നിൻ | Page 69","col":"holy-communion","colName":"Holy Communion"},{"n":"SS1","name":"ഒരിക്കൽ കൂടി ഞാൻ","name2":"Orikkal koodi njan","col":"birthday-anniversary","colName":"Birthday & Anniversary"},{"n":"SS2","name":"നന്ദിയാലെന്നുള്ളം തിങ്ങുകയാൽ | ക്രി. കീ. 434","name2":"Nandiyaalennullam thingukayaal | K. K. 434","col":"birthday-anniversary","colName":"Birthday & Anniversary"},{"n":"SS3","name":"ആരാധന രാജാധി രാജാവാം | മാരാമൺ 2008 - 61","name2":"Aaradhana Rajadhi Rajavaam | Maaramon 2008 - 61","col":"birthday-anniversary","colName":"Birthday & Anniversary"},{"n":"SS4","name":"തിരുക്കരത്താൽ വഹിച്ചു എന്നെ  | ക്രി. കീ. 453","name2":"Thirukkaratthal vahichchu enne | K. K. 453","col":"birthday-anniversary","colName":"Birthday & Anniversary"},{"n":"SS5","name":"എല്ലാം എല്ലാം ദാനമല്ലേ | മാരാമൺ 2009 - 63","name2":"Ellaam Ellaam Daanamalle | Maaramon 2009 - 63","col":"birthday-anniversary","colName":"Birthday & Anniversary"},{"n":"SS6","name":"എനിക്കല്ല ഞാൻ ക്രിസ്തുവിനത്രെ | മാരാമൺ 2009 - 89","name2":"Enikkal Njan Kristuvinathre | Maaramon 2009 - 89","col":"birthday-anniversary","colName":"Birthday & Anniversary"},{"n":"SS7","name":"സർവ്വവും യേശു നാഥനായ് | മാരാമൺ 2009 - 90","name2":"Sarvavum Yeshu Naathanay | Maaramon 2009 - 90","col":"birthday-anniversary","colName":"Birthday & Anniversary"},{"n":"SS8","name":"മറക്കില്ലൊരിക്കലും നീ ചെയ്ത ദാനങ്ങൾ | മാരാമൺ 2001 - 70","name2":"Marakkillorikkalum Nee Cheytha Daanangal | Maaramon 2001 - 70","col":"birthday-anniversary","colName":"Birthday & Anniversary"},{"n":"SS9","name":"ഉയരുന്നെന്നുള്ളിൽ സ്തോത്രത്തിൻ ഗാനം | ക്രി. കീ. 437","name2":"Uyarunnennullil Sthothrathin Gaanam | K. K. 437","col":"birthday-anniversary","colName":"Birthday & Anniversary"},{"n":"SS10","name":"എന്റെ കർത്താവേ തിരുസന്നിധിയിൽ | മാരാമൺ 2008 - 60","name2":"Ente Karthaave Thirusannidhiyil | Maaramon 2008 - 60","col":"birthday-anniversary","colName":"Birthday & Anniversary"},{"n":"SS11","name":"സർവ്വവും സമർപ്പിക്കുന്നേൻ | കൊട്ടാരക്കര 2011 - 69","name2":"Sarvavum Samarpikkunnen | Kottakara 2011 - 69","col":"birthday-anniversary","colName":"Birthday & Anniversary"},{"n":"SS12","name":"എന്നെന്നും നിന്നോട് പ്രാർഥിച്ചിടാനായ് | മാരാമൺ 2022 - 87","name2":"Ennennum Ninnodu Prarthichidanay | Maaramon 2022 - 87","col":"birthday-anniversary","colName":"Birthday & Anniversary"},{"n":"SS13","name":"ഇന്നയോളം നടത്തിയല്ലോ | മാരാമൺ 2011 - 96","name2":"Innayolam Nadathiyallo | Maaramon 2011 - 96","col":"birthday-anniversary","colName":"Birthday & Anniversary"},{"n":"SS14","name":"ദൈവ പിതാവേ അങ്ങയെ ഞാൻ","name2":"Daiva Pithave Angaye Njan","col":"birthday-anniversary","colName":"Birthday & Anniversary"},{"n":"SS15","name":"നന്ദിയോടെ ഞാൻ സ്തുതി | ക്രി. കീ. 435","name2":"Nandiyode Njan Stuthi | K. K. 435","col":"birthday-anniversary","colName":"Birthday & Anniversary"},{"n":6,"name":"Aaraadhikkaam namukkaaraadhikkaam","name2":"ആരാധിക്കാം നമുക്കാരാധിക്കാം","col":"kottarakara-2025","colName":"Kottarakara Convention 2025"},{"n":14,"name":"Alavillaa daanangal","name2":"അളവില്ലാ ദാനങ്ങള്‍","col":"kottarakara-2025","colName":"Kottarakara Convention 2025"},{"n":15,"name":"Enni Enni Sthuthikkuvaan","name2":"എണ്ണി എണ്ണി സ്തുതിക്കുവാൻ","col":"kottarakara-2025","colName":"Kottarakara Convention 2025"},{"n":39,"name":"Van Kripa Maaripol","name2":"വൻകൃപ മാരിപോൽ ","col":"kottarakara-2025","colName":"Kottarakara Convention 2025"},{"n":40,"name":"Jeevithamaam Yaathrayil","name2":"ജീവിതമാം യാത്രയിൽ","col":"kottarakara-2025","colName":"Kottarakara Convention 2025"},{"n":45,"name":"Yaahin Thirumozhikal","name2":"യാഹിൻ തിരുമൊഴികൾ","col":"kottarakara-2025","colName":"Kottarakara Convention 2025"},{"n":57,"name":"Paramonnathaa Parishudha Daivame","name2":"പരമോന്നതാ പരിശുദ്ധ ദൈവമേ","col":"kottarakara-2025","colName":"Kottarakara Convention 2025"},{"n":67,"name":"Anuranjanathin Samayamithaa","name2":"അനുരഞ്ജനത്തിൻ സമയമിതാ","col":"kottarakara-2025","colName":"Kottarakara Convention 2025"},{"n":85,"name":"Thalarenda Maname","name2":"തളരേണ്ട മനമേ","col":"kottarakara-2025","colName":"Kottarakara Convention 2025"},{"n":89,"name":"Athulyamaaya Divya Snehathaal","name2":"അതുല്യമായ ദിവ്യ സ്നേഹത്താൽ","col":"kottarakara-2025","colName":"Kottarakara Convention 2025"},{"n":30,"name":"Kadannu Poyoru Kaalamokkeyum","name2":"കടന്നു പോയൊരു കാലമൊക്കെയും","col":"kottarakara-2026","colName":"Kottarakara Convention 2026"},{"n":44,"name":"Vachanam Thiruvachanam","name2":"വചനം തിരുവചനം","col":"kottarakara-2026","colName":"Kottarakara Convention 2026"},{"n":46,"name":"Thiruvachanam Anudinam","name2":"തിരുവചനം അനുദിനം","col":"kottarakara-2026","colName":"Kottarakara Convention 2026"},{"n":71,"name":"Naathaa Nee Onnu Vanneedane","name2":"നാഥാ നീ ഒന്നു വന്നീടണെ","col":"kottarakara-2026","colName":"Kottarakara Convention 2026"},{"n":73,"name":"Nin Manamarinju Ninhitham Cheyyuvaan","name2":"നിൻ മനമറിഞ്ഞു നിൻഹിതം ചെയ്യുവാൻ","col":"kottarakara-2026","colName":"Kottarakara Convention 2026"},{"n":78,"name":"Karuthalodennum Kakkunna Devaa","name2":"കരുതലോടെന്നും കാക്കുന്ന ദേവാ","col":"kottarakara-2026","colName":"Kottarakara Convention 2026"},{"n":92,"name":"Daivathin Sneham","name2":"ദൈവത്തിൻ സ്നേഹം","col":"kottarakara-2026","colName":"Kottarakara Convention 2026"},{"n":93,"name":"Nandi Maathrame Nandi Daivame","name2":"നന്ദി മാത്രമെ നന്ദി ദൈവമെ","col":"kottarakara-2026","colName":"Kottarakara Convention 2026"}]