[
  {
    "number": 18,
    "name": "YAHE NINTE NAAMAM",
    "name2": "യഹേ നിന്റെ നാമം",
    "youtubeId": "7dUVukM76Pk"
  },
  {
    "number": 19,
    "name": "STHOTHRAM PAADEEDUKA",
    "name2": "സ്തോത്രം പാടീടുക",
    "youtubeId": "fJZ4Okua7WI"
  },
  {
    "number": 27,
    "name": "NAYANANGAL NIRAYUM",
    "name2": "നയനങ്ങൾ നിറയും",
    "youtubeId": "sSShHlO_pIg"
  },
  {
    "number": 28,
    "name": "THARALITHAMAYORU",
    "name2": "തരളിതമായൊരു",
    "youtubeId": "owA8vGwSTq0"
  },
  {
    "number": 29,
    "name": "KAARUNNYAVAANE",
    "name2": "കാരുണ്യവാനെ",
    "youtubeId": "YHrdFx9HF5o"
  },
  {
    "number": 35,
    "name": "KARUNA NIRANJAVANE",
    "name2": "കരുണ നിറഞ്ഞവനെ",
    "youtubeId": "eowJnIFiJZ0"
  },
  {
    "number": 36,
    "name": "DHAIVAME NANNIYAL",
    "name2": "ദൈവമെ നന്നിയാൽ",
    "youtubeId": "0ihgcYsqkgI"
  },
  {
    "number": 42,
    "name": "ANUNIMISHAM",
    "name2": "അനുനിമിഷം",
    "youtubeId": "0Ftx1SRPaI8"
  },
  {
    "number": 43,
    "name": "KRIPAMATHIYE",
    "name2": "ക്രിപമതിയെ",
    "youtubeId": "8yDygVRYzvI"
  },
  {
    "number": 44,
    "name": "YAHOVA EN",
    "name2": "യഹോവയെൻ",
    "youtubeId": "-zR4KmasBwk"
  },
  {
    "number": 55,
    "name": "ITHANAALUM NJAAN",
    "name2": "ഇത്രനാളും ഞാൻ",
    "youtubeId": "7OhkS7rvdQ4"
  },
  {
    "number": 66,
    "name": "VACHANAM THIRUVACHANAM",
    "name2": "വചനം തിരുവചനം",
    "youtubeId": "lZWIDvZgeDg"
  },
  {
    "number": 75,
    "name": "AATHMA PHALANGALAL",
    "name2": "അത്മ ഫലങ്ങളാൽ",
    "youtubeId": "RBqlzs8Cp58"
  },
  {
    "number": 90,
    "name": "BELAHEENATHAYIL",
    "name2": "ബേലഹീനതയിൽ",
    "youtubeId": "WbIHCDj52sY"
  },
  {
    "number": 91,
    "name": "KANNUNEER KANNUNNA",
    "name2": "കണ്ണുനീർ കാണുന്ന",
    "youtubeId": "vtsPwMn11tE"
  },
  {
    "number": 92,
    "name": "ANTHYATHOLAM",
    "name2": "അന്ത്യത്തോളം",
    "youtubeId": "Wa5PIbfDrLU"
  }
]